Workbook

Sheet 0. Executive Summary
B2: AIdeology × e& — ENTERPRISE Internal Pricing Summary
B3: Pillar 02 (Enterprise & Government). One page. Detail in tabs 1-11.
B5: A. WHAT ARE WE BUILDING?
B6: We extend the SMB platform with an enterprise-readiness layer (RBAC, audit, trust tiers, ERP/CRM/HIS integration, fine-tuning) and
B7: deliver three engagement tiers to e&'s enterprise & government customers:
B8: Tier 1 — adapted SMB agents with enterprise connectors (deeper, multi-branch, compliance, fine-tuned)
B9: Tier 2 — custom AI solutions including AI Contact Centre, Document Intelligence, Approvals, Predictive Maint., Security
B10: Tier 3 — sovereign / on-premise deployments (customer site) using pre-prepared HPC RA BoMs for vendor agility
B11: Each project can deploy on G42 / Core42 sovereign cloud, e& cloud, or customer on-prem. Custom bespoke engineering on demand.
B13: B. WHAT DOES IT COST US? (per build / per project — internal)
B14: Wave E0 — Platform extensions (one-off) | D14: Tier 1 cost — average per adapted agent | F14: Tier 2 cost — average per custom solution
B15: ='8. Pricing Summary'!C9 | D15: ='8. Pricing Summary'!C20 | F15: ='8. Pricing Summary'!C30
B17: Tier 3 cost — average sovereign / on-prem project | D17: Custom bespoke — average ~22-week build | F17: Managed service — monthly cost per client
B18: ='8. Pricing Summary'!C36 | D18: ='7. Custom Bespoke'!C26 | F18: ='8. Pricing Summary'!C41
B21: C. WHAT DO WE CHARGE e&? (price to e&)
B22: Wave E0 — Platform extensions price | D22: Tier 1 — average price per adapted agent | F22: Tier 2 — average price per custom solution
B23: ='8. Pricing Summary'!E9 | D23: ='8. Pricing Summary'!E20 | F23: ='8. Pricing Summary'!E30
B25: Tier 3 — average price per sovereign project | D25: Custom bespoke — average price | F25: Managed service — monthly price per client
B26: ='8. Pricing Summary'!E36 | D26: ='7. Custom Bespoke'!E26 | F26: ='8. Pricing Summary'!E41
B29: D. 3-YEAR REVENUE FORECAST (mid scenario)
C30: Year 1 | D30: Year 2 | E30: Year 3 | F30: 3-Year Total
B31: # Projects (Y1: 4, Y2: 11, Y3: 18 mid-scenario) | C31: ='9. Revenue Forecast'!C9 | D31: ='9. Revenue Forecast'!D9 | E31: ='9. Revenue Forecast'!E9 | F31: =SUM(C31:E31)
B32: Gross project & build revenue (e& sale price) | C32: ='9. Revenue Forecast'!C19 | D32: ='9. Revenue Forecast'!D19 | E32: ='9. Revenue Forecast'!E19 | F32: =SUM(C32:E32)
B33: Managed service recurring revenue | C33: ='9. Revenue Forecast'!C24 | D33: ='9. Revenue Forecast'!D24 | E33: ='9. Revenue Forecast'!E24 | F33: =SUM(C33:E33)
B34: AIdeology share (60% of project + 60% managed) | C34: ='9. Revenue Forecast'!C30 | D34: ='9. Revenue Forecast'!D30 | E34: ='9. Revenue Forecast'!E30 | F34: =SUM(C34:E34)
B35: e& share (40% project + 40% managed + hosting) | C35: ='9. Revenue Forecast'!C31 | D35: ='9. Revenue Forecast'!D31 | E35: ='9. Revenue Forecast'!E31 | F35: =SUM(C35:E35)
B37: E. THREE PRICING POSTURES
C38: Conservative | D38: Mid (baseline) | E38: Aggressive
B39: Tier 1 price per agent | C39: 30000 | D39: 55000 | E39: 80000
B40: Tier 2 price per project | C40: 300000 | D40: 450000 | E40: 600000
B41: Tier 3 price per project | C41: 600000 | D41: 800000 | E41: 1000000
B42: Best for | C42: AIdeology cash certainty | D42: JSX framework baseline | E42: Maximise margin on flagships
B43: Risk | C43: Leaves money on the table | D43: Balanced | E43: Slower pipeline
B44: F. KEY INSIGHTS
B45: SMB platform is the baseline. Tier 1 enterprise agents are NOT rebuilt — we add multi-branch, deep ERP/CRM/HIS connectors, compliance logging, and fine-tuning ON TOP. Average Tier 1 internal cost ~$100K (vs ~$240K to build an SMB wave from zero). For repeat agents on the same customer, the ERP integration work is amortised → second & third agents cost ~50% less.
B46: On-premise deployments are the most expensive (Tier 3) — but with pre-prepared HPC reference architectures (Cisco / Dell / HPE / Lenovo / Supermicro NVIDIA-Certified BoMs), AIdeology can spin up a customer-specific BoM in days, not weeks. See Sheet 10 for the BoM library.
B47: AI Contact Centre Software for Enterprises is delivered as the headline Tier 2 custom solution (Sheet 5). It packages voice + WhatsApp + web + agent assist + supervisor analytics on the AIdeology platform with deep CRM/ERP/HIS integration. Internal cost ~$374K → price to e& ~$680K @ 45% margin (above JSX $300-600K — verify per deal).

Sheet 1. Cover & Assumptions
B2: AIdeology — Enterprise Internal Pricing & Staffing Analysis
B3: e& B2B Acceleration · Pillar 02 — Enterprise & Government · v0.1 DRAFT
B4: INTERNAL — NOT FOR e&. Pricing model for AIdeology team only.
B5: Date: 2026-05-10
B7: How to use this workbook
B8: • Blue-text / yellow-shaded cells are editable inputs (rates, p-weeks, margins, deal counts).
B9: • Green-text cells are formulas — do not overwrite.
B10: • Sheet 2: Roles & Rates — same SMB roles + 4 enterprise-specific roles (ERP architect, Compliance SME, Industry SME, Fine-Tuning Eng).
B11: • Sheet 3: Wave E0 — Platform extensions on top of SMB platform (P1 + P2 layers, ~12 weeks).
B12: • Sheet 4: Tier 1 — Adapted SMB Agents (delta cost only — agents reuse SMB build).
B13: • Sheet 5: Tier 2 — Custom AI Solutions (Contact Centre, Doc Intel, Approvals, Pred Maint, Security).
B14: • Sheet 6: Tier 3 — Sovereign / On-Prem (uses pre-prepared HPC RA BoMs).
... B22: Global assumptions
B23: Assumption | C23: Value | D23: Unit | E23: Notes / source
B24: Working days per week | C24: 5 | D24: days | E24: Standard.
B25: Hours per working day | C25: 8 | D25: hours | E25: Standard.
B26: Currency | C26: USD | D26: — | E26: Internal model; price to e& issuable in USD or AED.
B27: FX assumption (USD→AED) | C27: 3.67 | D27: rate | E27: Pegged.
B28: Wave E0 — Platform extensions duration | C28: 12 | D28: weeks | E28: P1 enterprise-readiness + P2 government layer (RBAC, audit, trust tiers, ERP framework, fine-tuning sub-platform).
B29: Wave E0 target gross margin | C29: 0.45 | D29: % | E29: Reusable platform IP; reused across every Tier 1/2/3 deal.
B30: Tier 1 target gross margin | C30: 0.5 | D30: % | E30: Adapted SMB agent — minimal new build, mostly configuration & connectors. High margin justified.
B31: Tier 2 target gross margin | C31: 0.45 | D31: % | E31: Custom AI solution build — moderate complexity, controlled cloud.
B32: Tier 3 target gross margin | C32: 0.4 | D32: % | E32: Sovereign / on-prem — highest delivery risk + customer-specific work.
B33: Custom bespoke target gross margin | C33: 0.5 | D33: % | E33: Unique IP creation — premium pricing, risk-adjusted.
B34: Managed service target gross margin | C34: 0.55 | D34: % | E34: Recurring monthly support; high margin once stable.
B35: Contingency on direct cost (Tier 1) | C35: 0.1 | D35: % | E35: Buffer for unknowns.
B36: Contingency on direct cost (Tier 2) | C36: 0.12 | D36: % | E36: Higher — custom build risk.
B37: Contingency on direct cost (Tier 3) | C37: 0.15 | D37: % | E37: Highest — customer-site, networking, security review uncertainty.
B38: Risk reserve (held internally) | C38: 0.05 | D38: % | E38: Held at AIdeology level — not passed to e& in price.
... B52: Managed service ramp delay (months from project close) | C52: 1 | D52: months | E52: Begins immediately after go-live.
B55: Important disclaimers
B56: • Daily rates in Sheet 2 are PLACEHOLDER values to be validated against AIdeology's actual cost structure.
B57: • Per-tier p-weeks in Sheets 3-7 are first-pass sizing. Adjust based on deal scope per opportunity.
B58: • Tier 1 enterprise agents reuse the SMB platform build — only the delta work is costed here.
B59: • Tier 3 BoM costs in Sheet 10 are vendor MSRP indicative; e& negotiating power expected to discount 20-35%.
B60: • Help AG security wrap costs (~$50K-$100K) included on Tier 3; verify with Help AG quote per project.
B61: • Cloud costs depend on environment (e& OCI / G42 Core42 / Azure CSP via e&); revise once landing zone confirmed per deal.
B62: • Voice/STT/TTS costs (Deepgram, ElevenLabs, Azure Speech) estimated; replace with vendor quotes for large CCaaS deals.

Sheet 2. Roles & Rates
B2: Enterprise Roles & Daily Rates
B3: IN PLAIN ENGLISH: This is the Enterprise team. SMB roles + 4 enterprise specialists. The 'Internal cost' is what each person costs us per day.
B5: Role | C5: Seniority | D5: Internal cost / day (USD) | E5: Bill rate / day (USD) | F5: Notes
B6: Engagement / Programme Manager | C6: Senior | D6: 1000 | E6: 1750 | F6: Single point of contact to e&; weekly governance; commercial owner.
B7: Solution Architect (Lead) | C7: Principal | D7: 1100 | E7: 2100 | F7: Owns reference architecture, multi-tenant design, latency budget, capability matrix.
B8: AI / LLM Engineer — Orchestration & Reasoning | C8: Senior | D8: 900 | E8: 1700 | F8: Agent graph, FSM, tool-calling, memory, guardrails, Portkey integration.
B9: Voice / Conversational Engineer | C9: Senior | D9: 850 | E9: 1650 | F9: Telephony, STT/TTS, WhatsApp/Web channels, Arabic/English NLP.
B10: Data & Integration Engineer | C10: Senior | D10: 900 | E10: 1550 | F10: Connectors (CRM, calendar, payments), e& billing API, vector store, knowledge ingestion.
B11: Frontend / UX Engineer | C11: Mid | D11: 750 | E11: 1300 | F11: Next.js tenant back office, onboarding, admin console, agent configuration UI.
B12: DevOps / Platform Engineer | C12: Senior | D12: 950 | E12: 1550 | F12: Helm/Terraform, CI/CD, multi-tenant K8s, observability stack, secrets, cost guardrails.
B13: QA Engineer | C13: Mid | D13: 700 | E13: 1200 | F13: Test packs, synthetic data, automated regression, voice/chat acceptance tests.
B14: Security / Compliance Lead | C14: Senior | D14: 1050 | E14: 1750 | F14: Tenant isolation, NESA / TDRA / ADDA controls, pen-test coordination.
B15: Customer Success / Beta Ops Lead | C15: Mid | D15: 600 | E15: 950 | F15: Pilot onboarding, feedback loops, runbooks, support escalation.
B16: ERP / Systems Integration Architect | C16: Principal | D16: 1200 | E16: 2200 | F16: Oracle Fusion / SAP S/4HANA / Epic / Temenos / Dynamics deep integration. Critical for Tier 1/2/3 enterprise builds.
B17: Regulatory & Compliance SME | C17: Senior | D17: 1100 | E17: 1800 | F17: DHA / CBUAE / NESA / ADDA / FTA. Maps regulation to controls; named on every Tier 2/3 audit trail.
... B20: Hardware / On-Prem Infra Engineer (Tier 3) | C20: Senior | D20: 1000 | E20: 1700 | F20: On-customer-site GPU cluster install, networking, storage, NVAIE; coordinates with Help AG for security wrap.
B22: Total roles in plan: 15 (10 SMB-shared + 5 enterprise-specific)

Sheet 3. Wave E0 - Platform
B2: Wave E0 — Enterprise Platform Extensions (P1 + P2 layers on top of SMB platform)
B3: IN PLAIN ENGLISH: One-off build of the enterprise-readiness layer that Tier 1/2/3 deals reuse. RBAC, audit trail, trust tiers, ERP framework, fine-tuning sub-platform. ~12 weeks across 5 phases.
B5: Role | C5: EP1 — Mobilisation & SDD | D5: EP2 — Trust Tiers + RBAC + Audit | E5: EP3 — ERP/CRM/HIS Integration Framework | F5: EP4 — Fine-Tuning Sub-Platform | G5: EP5 — Hardening, Pen-Test, GA | H5: Total p-weeks | I5: Notes
B6: Phase duration (weeks) | C6: 2 | D6: 3 | E6: 3 | F6: 2 | G6: 2 | H6: =SUM(C6:G6)
B7: Engagement / Programme Manager | C7: 1 | D7: 1 | E7: 1 | F7: 1 | G7: 1 | H7: =SUM(C7:G7) | I7: Engagement coordination across the 12-week build.
B8: Solution Architect (Lead) | C8: 2 | D8: 2 | E8: 2 | F8: 1 | G8: 1 | H8: =SUM(C8:G8) | I8: Architects own trust tier framework, namespace design, audit pipeline, ERP integration patterns.
B9: AI / LLM Engineer — Orchestration & Reasoning | C9: 1 | D9: 2 | E9: 2 | F9: 2 | G9: 1 | H9: =SUM(C9:G9) | I9: Tools-calling adapters for ERP/CRM/HIS, SSO providers, audit emitters.
B10: Voice / Conversational Engineer | C10: 0 | D10: 0 | E10: 0 | F10: 0 | G10: 0 | H10: =SUM(C10:G10) | I10: —
B11: Data & Integration Engineer | C11: 1 | D11: 2 | E11: 3 | F11: 1 | G11: 1 | H11: =SUM(C11:G11) | I11: ERP/CRM/HIS connector framework (Oracle, SAP, Epic, Temenos, Dynamics).
B12: Frontend / UX Engineer | C12: 1 | D12: 2 | E12: 2 | F12: 1 | G12: 1 | H12: =SUM(C12:G12) | I12: Admin console: trust tier UI, RBAC, audit viewer, fine-tune dashboard.
B13: DevOps / Platform Engineer | C13: 2 | D13: 3 | E13: 2 | F13: 2 | G13: 2 | H13: =SUM(C13:G13) | I13: Tenant isolation, namespace-per-tenant (T2), kernel-sandboxed runtime (T3 prep).
B14: QA Engineer | C14: 1 | D14: 2 | E14: 2 | F14: 1 | G14: 2 | H14: =SUM(C14:G14) | I14: Security testing, compliance test pack, regression for trust-tier transitions.
B15: Security / Compliance Lead | C15: 2 | D15: 3 | E15: 2 | F15: 2 | G15: 2 | H15: =SUM(C15:G15) | I15: Owns NESA / ISO 27017/27018 / SOC 2 Type II uplift; engages pen-test partner.
B16: Customer Success / Beta Ops Lead | C16: 0 | D16: 0 | E16: 0 | F16: 0 | G16: 0 | H16: =SUM(C16:G16) | I16: —
B17: ERP / Systems Integration Architect | C17: 1 | D17: 1 | E17: 3 | F17: 1 | G17: 1 | H17: =SUM(C17:G17) | I17: Owns ERP integration patterns library — reusable across every Tier 1/2/3 deal.
B18: Regulatory & Compliance SME | C18: 1 | D18: 2 | E18: 2 | F18: 1 | G18: 2 | H18: =SUM(C18:G18) | I18: Maps DHA / CBUAE / NESA / ADDA controls to platform features; signs off on audit evidence.
... B21: Hardware / On-Prem Infra Engineer (Tier 3) | C21: 0 | D21: 0 | E21: 0 | F21: 0 | G21: 0 | H21: =SUM(C21:G21) | I21: —
B22: Total person-weeks per phase | C22: =SUM(C7:C21) | D22: =SUM(D7:D21) | E22: =SUM(E7:E21) | F22: =SUM(F7:F21) | G22: =SUM(G7:G21) | H22: =SUM(H7:H21)
B24: Personnel cost (USD)
B25: Personnel cost — sum across phases | H25: =(H7*'2. Roles & Rates'!D6+H8*'2. Roles & Rates'!D7+H9*'2. Roles & Rates'!D8+H10*'2. Roles & Rates'!D9+H11*'2. Roles & Rates'!D10+H12*'2. Roles & Rates'!D11+H13*'2. Roles & Rates'!D12+H14*'2. Roles & Rates'!D13+H15*'2. Roles & Rates'!D14+H16*'2. Roles & Rates'!D15+H17*'2. Roles & Rates'!D16+H18*'2. Roles & Rates'!D17+H19*'2. Roles & Rates'!D18+H20*'2. Roles & Rates'!D19+H21*'2. Roles & Rates'!D20)*'1. Cover & Assumptions'!$C$24
B26: Other costs (cloud, LLM, security tools, pen-test) | H26: 85000 | I26: Cloud dev/staging, LLM gateway, observability, pen-test ($25K), security tools, contingency cushion. Editable.
B27: Direct cost — sum | H27: =H25+H26
B28: Contingency (12% — moderate complexity) | H28: =H27*0.12
B29: Total fully-loaded cost | H29: =H27+H28

Sheet 4. Tier 1 - Adapted Agents
B2: Tier 1 — Adapted SMB Agents (Enterprise Edition)
B3: IN PLAIN ENGLISH: Each enterprise customer gets adapted versions of the SMB agents — same agent IP, but with multi-branch routing, deep ERP/CRM/HIS connectors, compliance logging, fine-tuning. We DON'T rebuild the agent — we configure & extend it. That is why the cost is only ~$30-60K per agent.
B5: Role | C5: Cost / day | D5: Customer Agent (Enterprise) | E5: Sales Agent (Enterprise) | F5: Comms Hub (Enterprise) | G5: Finance Agent (Enterprise) | H5: Ops Agent (Enterprise) | I5: People Agent (Enterprise) | J5: Total p-weeks | K5: Notes
B6: Engagement / Programme Manager | C6: ='2. Roles & Rates'!D6 | D6: 1 | E6: 1 | F6: 1 | G6: 1 | H6: 1 | I6: 1 | J6: =SUM(D6:I6) | K6: Engagement & e&-customer coordination.
B7: Solution Architect (Lead) | C7: ='2. Roles & Rates'!D7 | D7: 1 | E7: 1 | F7: 1 | G7: 1 | H7: 1 | I7: 1 | J7: =SUM(D7:I7) | K7: Solution architect signs off integration design + trust tier mapping.
B8: AI / LLM Engineer — Orchestration & Reasoning | C8: ='2. Roles & Rates'!D8 | D8: 2 | E8: 2 | F8: 2 | G8: 2 | H8: 2 | I8: 2 | J8: =SUM(D8:I8) | K8: Enterprise prompt tuning + new tools per ERP/CRM/HIS context.
B9: Voice / Conversational Engineer | C9: ='2. Roles & Rates'!D9 | D9: 1 | E9: 0 | F9: 2 | G9: 0 | H9: 0 | I9: 0 | J9: =SUM(D9:I9) | K9: Voice only on Customer Agent + Comms Hub (multi-branch IVR).
B10: Data & Integration Engineer | C10: ='2. Roles & Rates'!D10 | D10: 3 | E10: 3 | F10: 3 | G10: 4 | H10: 3 | I10: 4 | J10: =SUM(D10:I10) | K10: Heaviest role — connector to customer's ERP/CRM/HIS instance.
B11: Frontend / UX Engineer | C11: ='2. Roles & Rates'!D11 | D11: 1 | E11: 1 | F11: 1 | G11: 1 | H11: 1 | I11: 1 | J11: =SUM(D11:I11) | K11: Light UI tweaks — multi-branch routing, custom branding.
B12: DevOps / Platform Engineer | C12: ='2. Roles & Rates'!D12 | D12: 1 | E12: 1 | F12: 1 | G12: 1 | H12: 1 | I12: 1 | J12: =SUM(D12:I12) | K12: Tenant onboarding into customer's environment + observability hooks.
B13: QA Engineer | C13: ='2. Roles & Rates'!D13 | D13: 1 | E13: 1 | F13: 1 | G13: 2 | H13: 1 | I13: 2 | J13: =SUM(D13:I13) | K13: Per-agent acceptance tests + compliance test pack.
B14: Security / Compliance Lead | C14: ='2. Roles & Rates'!D14 | D14: 1 | E14: 1 | F14: 1 | G14: 2 | H14: 1 | I14: 2 | J14: =SUM(D14:I14) | K14: Compliance logging + audit trail wiring + RBAC config.
B15: Customer Success / Beta Ops Lead | C15: ='2. Roles & Rates'!D15 | D15: 1 | E15: 1 | F15: 1 | G15: 1 | H15: 1 | I15: 1 | J15: =SUM(D15:I15) | K15: Pilot user onboarding + hypercare for 30 days.
B16: ERP / Systems Integration Architect | C16: ='2. Roles & Rates'!D16 | D16: 2 | E16: 2 | F16: 2 | G16: 3 | H16: 2 | I16: 3 | J16: =SUM(D16:I16) | K16: Critical role — Oracle Fusion / SAP S/4HANA / Epic / Temenos / Dynamics integration.
B17: Regulatory & Compliance SME | C17: ='2. Roles & Rates'!D17 | D17: 1 | E17: 1 | F17: 1 | G17: 2 | H17: 1 | I17: 2 | J17: =SUM(D17:I17) | K17: Maps customer-specific compliance (DHA / CBUAE / NESA / ADDA) to controls.
... B20: Hardware / On-Prem Infra Engineer (Tier 3) | C20: ='2. Roles & Rates'!D20 | D20: 0 | E20: 0 | F20: 0 | G20: 0 | H20: 0 | I20: 0 | J20: =SUM(D20:I20) | K20: —
B21: Total person-weeks per agent | D21: =SUM(D6:D20) | E21: =SUM(E6:E20) | F21: =SUM(F6:F20) | G21: =SUM(G6:G20) | H21: =SUM(H6:H20) | I21: =SUM(I6:I20) | J21: =SUM(J6:J20)
B23: Cost per agent (USD)
B24: Item | C24: Customer Agent (Enterprise) | D24: Sales Agent (Enterprise) | E24: Comms Hub (Enterprise) | F24: Finance Agent (Enterprise) | G24: Ops Agent (Enterprise) | H24: People Agent (Enterprise) | I24: Avg per agent
B25: Personnel cost | D25: =(D6*$C6+D7*$C7+D8*$C8+D9*$C9+D10*$C10+D11*$C11+D12*$C12+D13*$C13+D14*$C14+D15*$C15+D16*$C16+D17*$C17+D18*$C18+D19*$C19+D20*$C20)*'1. Cover & Assumptions'!$C$24 | E25: =(E6*$C6+E7*$C7+E8*$C8+E9*$C9+E10*$C10+E11*$C11+E12*$C12+E13*$C13+E14*$C14+E15*$C15+E16*$C16+E17*$C17+E18*$C18+E19*$C19+E20*$C20)*'1. Cover & Assumptions'!$C$24 | F25: =(F6*$C6+F7*$C7+F8*$C8+F9*$C9+F10*$C10+F11*$C11+F12*$C12+F13*$C13+F14*$C14+F15*$C15+F16*$C16+F17*$C17+F18*$C18+F19*$C19+F20*$C20)*'1. Cover & Assumptions'!$C$24 | G25: =(G6*$C6+G7*$C7+G8*$C8+G9*$C9+G10*$C10+G11*$C11+G12*$C12+G13*$C13+G14*$C14+G15*$C15+G16*$C16+G17*$C17+G18*$C18+G19*$C19+G20*$C20)*'1. Cover & Assumptions'!$C$24 | H25: =(H6*$C6+H7*$C7+H8*$C8+H9*$C9+H10*$C10+H11*$C11+H12*$C12+H13*$C13+H14*$C14+H15*$C15+H16*$C16+H17*$C17+H18*$C18+H19*$C19+H20*$C20)*'1. Cover & Assumptions'!$C$24 | I25: =(I6*$C6+I7*$C7+I8*$C8+I9*$C9+I10*$C10+I11*$C11+I12*$C12+I13*$C13+I14*$C14+I15*$C15+I16*$C16+I17*$C17+I18*$C18+I19*$C19+I20*$C20)*'1. Cover & Assumptions'!$C$24 | J25: =AVERAGE(D25:I25)
B26: Other costs (per agent — sandbox, fine-tune compute, integration env) | D26: 8000 | E26: 8000 | F26: 8000 | G26: 8000 | H26: 8000 | I26: 8000 | J26: =AVERAGE(D26:I26)
B27: Total cost per agent (Tier 1) | D27: =D25+D26 | E27: =E25+E26 | F27: =F25+F26 | G27: =G25+G26 | H27: =H25+H26 | I27: =I25+I26 | J27: =AVERAGE(D27:I27)
B29: ↑ Note: cost EXCLUDES Wave E0 platform extensions (one-off in Sheet 3) and any Help AG security wrap (Tier 3 only).

Sheet 5. Tier 2 - Custom AI
B2: Tier 2 — Custom AI Solutions (incl. AI Contact Centre Software for Enterprises)
B3: IN PLAIN ENGLISH: Bigger custom AI solutions that go beyond the marketplace agents. AI Contact Centre is the headline solution — full CCaaS with voice, WhatsApp, web, agent assist, supervisor analytics, deep ERP/CRM/HIS integration. ~16-24 weeks per project.
B5: Role | C5: Cost / day | D5: AI Contact Centre Software (Enterprise) | E5: Document Intelligence Suite | F5: Approval Orchestration Platform | G5: Predictive Maintenance Agent | H5: Security & Compliance Agent | I5: Notes
B6: Engagement / Programme Manager | C6: ='2. Roles & Rates'!D6 | D6: 4 | E6: 4 | F6: 3 | G6: 4 | H6: 4 | I6: Engagement coordination across the 16-22 week build.
B7: Solution Architect (Lead) | C7: ='2. Roles & Rates'!D7 | D7: 3 | E7: 3 | F7: 3 | G7: 3 | H7: 3 | I7: Architect owns SDD, integration design, latency budget, fallback strategy.
B8: AI / LLM Engineer — Orchestration & Reasoning | C8: ='2. Roles & Rates'!D8 | D8: 10 | E8: 8 | F8: 8 | G8: 8 | H8: 8 | I8: Heaviest role — orchestration, prompt engineering, evals, tool calling.
B9: Voice / Conversational Engineer | C9: ='2. Roles & Rates'!D9 | D9: 12 | E9: 0 | F9: 0 | G9: 0 | H9: 0 | I9: CCaaS only — STT/TTS, real-time transcription, agent assist, post-call summary.
B10: Data & Integration Engineer | C10: ='2. Roles & Rates'!D10 | D10: 10 | E10: 8 | F10: 6 | G10: 10 | H10: 6 | I10: ERP/CRM/HIS integration; CCaaS = CRM screen-pop + ticket creation.
B11: Frontend / UX Engineer | C11: ='2. Roles & Rates'!D11 | D11: 6 | E11: 6 | F11: 6 | G11: 4 | H11: 4 | I11: Supervisor/agent UI; CCaaS = wallboards, queue mgmt; Doc Intel = review UI.
B12: DevOps / Platform Engineer | C12: ='2. Roles & Rates'!D12 | D12: 4 | E12: 3 | F12: 3 | G12: 4 | H12: 3 | I12: Per-project deployment + observability + cost guardrails.
B13: QA Engineer | C13: ='2. Roles & Rates'!D13 | D13: 5 | E13: 5 | F13: 4 | G13: 5 | H13: 4 | I13: Heavy test coverage — voice acceptance, regression, regulator scenarios.
B14: Security / Compliance Lead | C14: ='2. Roles & Rates'!D14 | D14: 3 | E14: 3 | F14: 4 | G14: 3 | H14: 6 | I14: Security & Compliance Agent peaks here; others moderate.
B15: Customer Success / Beta Ops Lead | C15: ='2. Roles & Rates'!D15 | D15: 4 | E15: 3 | F15: 3 | G15: 3 | H15: 3 | I15: Pilot user onboarding + 30-day hypercare per project.
B16: ERP / Systems Integration Architect | C16: ='2. Roles & Rates'!D16 | D16: 4 | E16: 4 | F16: 4 | G16: 4 | H16: 3 | I16: Deep integration to customer ERP — CCaaS needs ticketing system bridge.
B17: Regulatory & Compliance SME | C17: ='2. Roles & Rates'!D17 | D17: 3 | E17: 3 | F17: 4 | G17: 2 | H17: 5 | I17: Compliance Agent needs heaviest SME involvement — full regulatory mapping.
... B20: Hardware / On-Prem Infra Engineer (Tier 3) | C20: ='2. Roles & Rates'!D20 | D20: 0 | E20: 0 | F20: 0 | G20: 0 | H20: 0 | I20: —
B21: Total person-weeks per project | D21: =SUM(D6:D20) | E21: =SUM(E6:E20) | F21: =SUM(F6:F20) | G21: =SUM(G6:G20) | H21: =SUM(H6:H20)
B23: Cost per project (USD)
B24: Item | C24: AI Contact Centre Software (Enterprise) | D24: Document Intelligence Suite | E24: Approval Orchestration Platform | F24: Predictive Maintenance Agent | G24: Security & Compliance Agent | H24: Avg per project
B25: Personnel cost | D25: =(D6*$C6+D7*$C7+D8*$C8+D9*$C9+D10*$C10+D11*$C11+D12*$C12+D13*$C13+D14*$C14+D15*$C15+D16*$C16+D17*$C17+D18*$C18+D19*$C19+D20*$C20)*'1. Cover & Assumptions'!$C$24 | E25: =(E6*$C6+E7*$C7+E8*$C8+E9*$C9+E10*$C10+E11*$C11+E12*$C12+E13*$C13+E14*$C14+E15*$C15+E16*$C16+E17*$C17+E18*$C18+E19*$C19+E20*$C20)*'1. Cover & Assumptions'!$C$24 | F25: =(F6*$C6+F7*$C7+F8*$C8+F9*$C9+F10*$C10+F11*$C11+F12*$C12+F13*$C13+F14*$C14+F15*$C15+F16*$C16+F17*$C17+F18*$C18+F19*$C19+F20*$C20)*'1. Cover & Assumptions'!$C$24 | G25: =(G6*$C6+G7*$C7+G8*$C8+G9*$C9+G10*$C10+G11*$C11+G12*$C12+G13*$C13+G14*$C14+G15*$C15+G16*$C16+G17*$C17+G18*$C18+G19*$C19+G20*$C20)*'1. Cover & Assumptions'!$C$24 | H25: =(H6*$C6+H7*$C7+H8*$C8+H9*$C9+H10*$C10+H11*$C11+H12*$C12+H13*$C13+H14*$C14+H15*$C15+H16*$C16+H17*$C17+H18*$C18+H19*$C19+H20*$C20)*'1. Cover & Assumptions'!$C$24 | I25: =AVERAGE(D25:H25)
B26: Other costs (cloud, LLM, voice APIs, sandbox) | D26: 40000 | E26: 25000 | F26: 20000 | G26: 25000 | H26: 20000 | I26: =AVERAGE(D26:H26)
B27: Total cost per project (Tier 2) | D27: =D25+D26 | E27: =E25+E26 | F27: =F25+F26 | G27: =G25+G26 | H27: =H25+H26 | I27: =AVERAGE(D27:H27)
B30: Solution descriptions
B31: AI Contact Centre Software (Enterprise) | C31: Full CCaaS — voice + WhatsApp + web + agent assist + supervisor + analytics.
B32: Document Intelligence Suite | C32: Inbound docs (forms, contracts, invoices, medical records) classified, extracted, routed.
B33: Approval Orchestration Platform | C33: Multi-step approvals with policy + RAG + human-in-loop (procurement, expenses, credit).
B34: Predictive Maintenance Agent | C34: IoT/SCADA telemetry → anomaly detection + work-order automation + technician dispatch.
B35: Security & Compliance Agent | C35: AI SOC analyst, log triage, compliance evidence, regulator reporting.

Sheet 6. Tier 3 - Sovereign OnPrem
B2: Tier 3 — Sovereign & On-Prem Deployments
B3: IN PLAIN ENGLISH: Customer-site deployments (gov, banks, healthcare regulators). Higher complexity — customer-specific architecture, networking, security, audit. Pre-prepared HPC RA BoMs (Sheet 10) let us spin up vendor-agnostic BoMs in days. Help AG security wrap included.
B5: Cost stack — typical Tier 3 sovereign / on-prem deployment
B6: Cost component | C6: Value (USD) | D6: Notes
B7: Base custom AI solution build (avg Tier 2 personnel) | C7: ='5. Tier 2 - Custom AI'!I27 | D7: References Tier 2 average personnel cost (Doc Intel / Approvals / Pred Maint median build).
B8: On-prem uplift — installation, networking, identity (8 wks Hardware Eng + Sec Lead) | C8: =8*'1. Cover & Assumptions'!$C$24*('2. Roles & Rates'!D20+'2. Roles & Rates'!D14) | D8: 8 weeks × 5 days × (Hardware Eng + Security Lead). Customer-site networking, AD/SSO integration, hardening.
B9: Customer-specific architecture & SDD addendum (3 wks Sol Arch + ERP Arch) | C9: =3*'1. Cover & Assumptions'!$C$24*('2. Roles & Rates'!D7+'2. Roles & Rates'!D16) | D9: 3-week architecture deep-dive with customer IT + procurement before build starts.
B10: On-prem environment & integration sandbox | C10: 25000 | D10: Bare-metal lab in AIdeology / e& staging that mirrors customer footprint for testing.
B11: Help AG managed security wrap | C11: 75000 | D11: Third-party security partner — pen-test, SOC integration, NESA evidence. Indicative — verify per project.
B12: HPC BoM coordination & vendor liaison (allowance) | C12: 25000 | D12: AIdeology engineering time to liaise with chosen vendor (Cisco/Dell/HPE/Lenovo/Supermicro) on BoM, lead times, install.
B13: Travel & on-site presence (4 trips × 5 people × 5 days) | C13: 60000 | D13: On-site mobilisation, install, UAT, go-live.
B14: Other costs (cloud, LLM, sandbox uplift) | C14: 30000 | D14: Higher than Tier 2 — air-gapped test env, dual-stack.
B15: Direct cost — sum | C15: =SUM(C7:C14)
B16: Contingency (15% — high-complexity buffer) | C16: =C15*'1. Cover & Assumptions'!$C$37
B17: Total fully-loaded cost — typical Tier 3 project | C17: =C15+C16
B20: ↑ Important — Hardware BoM is NOT in our cost above
B21: The HPC compute infrastructure (GPU cluster, networking, storage) is sold as a pass-through line via the chosen OEM (Cisco / Dell / HPE / Lenovo / Supermicro).
B22: AIdeology coordinates the BoM (allowance included above), sizes the cluster against customer workload, but does not carry hardware revenue. e& or the OEM owns that line.
B23: See Sheet 10 — HPC RA Library — for ten reference architectures from five vendors with sizing guidance (4-128 nodes, RTX PRO / HGX / B300 / NVL72).
B24: Optional: AIdeology can bundle the BoM into the price (with a 5-10% margin) — discuss per deal. Default model: hardware sold separately by OEM.

Sheet 7. Custom Bespoke
B2: Custom Bespoke Solutions (AIdeology unique builds)
B3: IN PLAIN ENGLISH: When an enterprise needs something that doesn't fit Tier 1/2/3 — a unique vertical AI, a moonshot R&D project, or new platform IP. Priced T&M or fixed-bid, premium margin (50%) because of unique IP and execution risk.
B5: Reference bespoke project sizing (~22 weeks, 8-person team)
B6: Role | C6: Cost / day | D6: p-weeks | E6: Personnel cost | F6: Notes
B7: Engagement / Programme Manager | C7: ='2. Roles & Rates'!D6 | D7: 5 | E7: =C7*D7*'1. Cover & Assumptions'!$C$24 | G7: PM
B8: Solution Architect (Lead) | C8: ='2. Roles & Rates'!D7 | D8: 6 | E8: =C8*D8*'1. Cover & Assumptions'!$C$24 | G8: Sol Arch
B9: AI / LLM Engineer — Orchestration & Reasoning | C9: ='2. Roles & Rates'!D8 | D9: 15 | E9: =C9*D9*'1. Cover & Assumptions'!$C$24 | G9: AI/LLM Eng (heavy R&D)
B10: Voice / Conversational Engineer | C10: ='2. Roles & Rates'!D9 | D10: 3 | E10: =C10*D10*'1. Cover & Assumptions'!$C$24 | G10: Voice (if needed)
B11: Data & Integration Engineer | C11: ='2. Roles & Rates'!D10 | D11: 10 | E11: =C11*D11*'1. Cover & Assumptions'!$C$24 | G11: Data/Integration
B12: Frontend / UX Engineer | C12: ='2. Roles & Rates'!D11 | D12: 8 | E12: =C12*D12*'1. Cover & Assumptions'!$C$24 | G12: Frontend
B13: DevOps / Platform Engineer | C13: ='2. Roles & Rates'!D12 | D13: 4 | E13: =C13*D13*'1. Cover & Assumptions'!$C$24 | G13: DevOps
B14: QA Engineer | C14: ='2. Roles & Rates'!D13 | D14: 6 | E14: =C14*D14*'1. Cover & Assumptions'!$C$24 | G14: QA
B15: Security / Compliance Lead | C15: ='2. Roles & Rates'!D14 | D15: 4 | E15: =C15*D15*'1. Cover & Assumptions'!$C$24 | G15: Security/Compliance
B16: Customer Success / Beta Ops Lead | C16: ='2. Roles & Rates'!D15 | D16: 3 | E16: =C16*D16*'1. Cover & Assumptions'!$C$24 | G16: CS / Beta Ops
B17: ERP / Systems Integration Architect | C17: ='2. Roles & Rates'!D16 | D17: 3 | E17: =C17*D17*'1. Cover & Assumptions'!$C$24 | G17: ERP Architect (if needed)
B18: Regulatory & Compliance SME | C18: ='2. Roles & Rates'!D17 | D18: 3 | E18: =C18*D18*'1. Cover & Assumptions'!$C$24 | G18: Compliance SME
... B21: Hardware / On-Prem Infra Engineer (Tier 3) | C21: ='2. Roles & Rates'!D20 | D21: 0 | E21: =C21*D21*'1. Cover & Assumptions'!$C$24 | G21: Hardware (only if on-prem)
B22: Total — bespoke build personnel | D22: =SUM(D7:D21) | E22: =SUM(E7:E21)
B23: Other costs (cloud, LLM, R&D compute, fine-tune, sandbox) | E23: 45000
B24: Direct cost — sum | E24: =E22+E23
B25: Contingency (15% — bespoke risk) | E25: =E24*0.15
B26: Total fully-loaded bespoke cost | C26: =E24+E25 | D26: @ 50% margin → | E26: =C26/(1-'1. Cover & Assumptions'!$C$33)
B29: Alternative — T&M model
B30: Blended bill rate (USD/day) | E30: 1500 | G30: Blended bill rate across the 15-person team. Editable.
B31: Estimated T&M billing for reference build | E31: =D22*'1. Cover & Assumptions'!$C$24*E30 | G31: Total p-weeks × 5 days × blended bill rate. Compare to fixed-bid above.

Sheet 8. Pricing Summary
B2: Pricing Summary — Cost → Margin → Price to e&
B3: IN PLAIN ENGLISH: Each tier's internal cost grossed up to a price using the target margin from Sheet 1. Price to e& = cost / (1 - margin).
B5: Component | C5: Total cost | D5: Margin (USD) | E5: Price to e& | F5: Notes
B8: A. Wave E0 — Enterprise Platform Extensions
B9: Wave E0 — one-off platform build | C9: ='3. Wave E0 - Platform'!H29 | D9: =C9/(1-'1. Cover & Assumptions'!$C$29)-C9 | E9: =C9+D9 | F9: One-off charged to first 1-2 enterprise deals or amortised across the first 4-5 deals (commercial choice).
B12: B. Tier 1 — Adapted SMB Agents (per agent)
B13: Agent (Tier 1) | C13: Cost | D13: Margin | E13: Price to e& | F13: Notes
B14: Customer Agent | C14: ='4. Tier 1 - Adapted Agents'!D27 | D14: =C14/(1-'1. Cover & Assumptions'!$C$30)-C14 | E14: =C14+D14 | F14: Tier 1 enterprise edition of the SMB Customer Agent.
B15: Sales Agent | C15: ='4. Tier 1 - Adapted Agents'!E27 | D15: =C15/(1-'1. Cover & Assumptions'!$C$30)-C15 | E15: =C15+D15 | F15: Tier 1 enterprise edition of the SMB Sales Agent.
B16: Comms Hub | C16: ='4. Tier 1 - Adapted Agents'!F27 | D16: =C16/(1-'1. Cover & Assumptions'!$C$30)-C16 | E16: =C16+D16 | F16: Tier 1 enterprise edition of the SMB Comms Hub.
B17: Finance Agent | C17: ='4. Tier 1 - Adapted Agents'!G27 | D17: =C17/(1-'1. Cover & Assumptions'!$C$30)-C17 | E17: =C17+D17 | F17: Tier 1 enterprise edition of the SMB Finance Agent.
B18: Ops Agent | C18: ='4. Tier 1 - Adapted Agents'!H27 | D18: =C18/(1-'1. Cover & Assumptions'!$C$30)-C18 | E18: =C18+D18 | F18: Tier 1 enterprise edition of the SMB Ops Agent.
B19: People Agent | C19: ='4. Tier 1 - Adapted Agents'!I27 | D19: =C19/(1-'1. Cover & Assumptions'!$C$30)-C19 | E19: =C19+D19 | F19: Tier 1 enterprise edition of the SMB People Agent.
B20: ↑ Tier 1 average per agent | C20: =AVERAGE(C14:C19) | D20: =AVERAGE(D14:D19) | E20: =AVERAGE(E14:E19)
B23: C. Tier 2 — Custom AI Solutions (per project)
B24: Solution (Tier 2) | C24: Cost | D24: Margin | E24: Price to e& | F24: Notes
B25: AI Contact Centre Software | C25: ='5. Tier 2 - Custom AI'!D27 | D25: =C25/(1-'1. Cover & Assumptions'!$C$31)-C25 | E25: =C25+D25 | F25: Tier 2 — fits in JSX framework $300K-$600K range.
B26: Document Intelligence | C26: ='5. Tier 2 - Custom AI'!E27 | D26: =C26/(1-'1. Cover & Assumptions'!$C$31)-C26 | E26: =C26+D26 | F26: Tier 2 — fits in JSX framework $300K-$600K range.
B27: Approval Orchestration | C27: ='5. Tier 2 - Custom AI'!F27 | D27: =C27/(1-'1. Cover & Assumptions'!$C$31)-C27 | E27: =C27+D27 | F27: Tier 2 — fits in JSX framework $300K-$600K range.
B28: Predictive Maintenance | C28: ='5. Tier 2 - Custom AI'!G27 | D28: =C28/(1-'1. Cover & Assumptions'!$C$31)-C28 | E28: =C28+D28 | F28: Tier 2 — fits in JSX framework $300K-$600K range.
B29: Security & Compliance | C29: ='5. Tier 2 - Custom AI'!H27 | D29: =C29/(1-'1. Cover & Assumptions'!$C$31)-C29 | E29: =C29+D29 | F29: Tier 2 — fits in JSX framework $300K-$600K range.
B30: ↑ Tier 2 average per project | C30: =AVERAGE(C25:C29) | D30: =AVERAGE(D25:D29) | E30: =AVERAGE(E25:E29)
B33: D. Tier 3 — Sovereign / On-Prem (per project)
B34: Component | C34: Cost | D34: Margin | E34: Price to e& | F34: Notes
B36: Tier 3 — typical sovereign / on-prem build | C36: ='6. Tier 3 - Sovereign OnPrem'!C17 | D36: =C36/(1-'1. Cover & Assumptions'!$C$32)-C36 | E36: =C36+D36 | F36: Tier 3 typically prices in the $600K-$1M JSX band. Hardware BoM sold separately by OEM. See Sheet 6 for the cost stack.
B39: E. Managed Service (per client per month)
B40: Component | C40: Cost / month | D40: Margin | E40: Price to e& / month | F40: Notes
B41: Managed service — typical | C41: 5400 | D41: =C41/(1-'1. Cover & Assumptions'!$C$34)-C41 | E41: =C41+D41 | F41: Cross-check: assumption ARPU = '1. Cover & Assumptions'!$C$50 ($12K/mo). Editable cost cell.
B44: F. Reality check — internal price vs JSX commercial framework
B45: Component | C45: Internal price | D45: JSX low | E45: JSX high | F45: Notes
B46: Tier 1 — average per agent | C46: =E20 | D46: 30000 | E46: 80000 | F46: Internal model is well above JSX top end — JSX assumed near-trivial config; reality requires real ERP integration. Reduce p-weeks if rolling out the same agent to a customer's 2nd/3rd seat (ERP work amortised).
B47: Tier 2 — average per project | C47: =E30 | D47: 300000 | E47: 600000 | F47: Mid range fits, but the AI Contact Centre solution lands above the JSX top end. Negotiable — see Sheet 5.
B48: Tier 3 — typical per project | C48: =E36 | D48: 600000 | E48: 1000000 | F48: Internal model just above JSX top end. Sovereign deals routinely exceed $1M; ok to set Tier 3 ceiling at $1.2-1.5M for premium gov/bank flagships.
B49: Custom bespoke | C49: ='7. Custom Bespoke'!E26 | D49: 400000 | E49: 800000 | F49: JSX did not publish a custom bespoke price band. Use Sheet 7 fixed-bid or T&M model per opportunity.
B50: Managed service per client / month | C50: =E41 | D50: 5000 | E50: 25000 | F50: $12K/mo lands in the JSX $5K-$25K band ✓
B52: G. Tier 1 amortised — 2nd / 3rd agent for the same enterprise customer
B53: Scenario | C53: Cost (USD) | D53: Margin | E53: Price to e& | F53: Notes
B54: Tier 1 — 1st agent for new customer (full) | C54: =C20 | D54: =C54/(1-'1. Cover & Assumptions'!$C$30)-C54 | E54: =C54+D54 | F54: Full ERP/SSO/audit work.
B55: Tier 1 — 2nd agent for same customer (~60%) | C55: =C20*0.60 | D55: =C55/(1-'1. Cover & Assumptions'!$C$30)-C55 | E55: =C55+D55 | F55: ERP connector reused; only agent-specific config + UAT.
B56: Tier 1 — 3rd+ agent for same customer (~50%) | C56: =C20*0.50 | D56: =C56/(1-'1. Cover & Assumptions'!$C$30)-C56 | E56: =C56+D56 | F56: Most integration plumbing already in place; mostly prompt tuning + UAT.

Sheet 9. Revenue Forecast
B2: 3-Year Revenue Forecast — Pipeline × Tier Mix → AIdeology vs e&
B3: IN PLAIN ENGLISH: Number of deals per year × tier mix × price per tier = gross revenue. Apply 60/40 AIdeology/e& split. Add managed service ramp.
B5: A. Deal volumes (mid scenario)
B6: Metric | C6: Year 1 | D6: Year 2 | E6: Year 3 | F6: 3-Year Total | G6: Notes
B9: # Total deals | C9: ='1. Cover & Assumptions'!$C$42 | D9: ='1. Cover & Assumptions'!$C$43 | E9: ='1. Cover & Assumptions'!$C$44 | F9: =SUM(C9:E9)
B10: # Tier 1 deals (= Total × Tier1 mix %) | C10: =C9*'1. Cover & Assumptions'!$C$45 | D10: =D9*'1. Cover & Assumptions'!$C$45 | E10: =E9*'1. Cover & Assumptions'!$C$45 | F10: =SUM(C10:E10)
B11: # Tier 1 agents in pipeline (× avg agents/deal) | C11: =C10*'1. Cover & Assumptions'!$C$49 | D11: =D10*'1. Cover & Assumptions'!$C$49 | E11: =E10*'1. Cover & Assumptions'!$C$49 | F11: =SUM(C11:E11)
B12: # Tier 2 deals | C12: =C9*'1. Cover & Assumptions'!$C$46 | D12: =D9*'1. Cover & Assumptions'!$C$46 | E12: =E9*'1. Cover & Assumptions'!$C$46 | F12: =SUM(C12:E12)
B13: # Tier 3 deals | C13: =C9*'1. Cover & Assumptions'!$C$47 | D13: =D9*'1. Cover & Assumptions'!$C$47 | E13: =E9*'1. Cover & Assumptions'!$C$47 | F13: =SUM(C13:E13)
B14: # Custom bespoke deals | C14: =C9*'1. Cover & Assumptions'!$C$48 | D14: =D9*'1. Cover & Assumptions'!$C$48 | E14: =E9*'1. Cover & Assumptions'!$C$48 | F14: =SUM(C14:E14)
B17: B. Gross revenue to e& (price × volume)
B18: Stream | C18: Year 1 | D18: Year 2 | E18: Year 3 | F18: 3-Year Total | G18: Notes
B19: Gross project revenue (build fees) | C19: =C11*'8. Pricing Summary'!$E$20+C12*'8. Pricing Summary'!$E$30+C13*'8. Pricing Summary'!$E$36+C14*'7. Custom Bespoke'!$E$26 | D19: =D11*'8. Pricing Summary'!$E$20+D12*'8. Pricing Summary'!$E$30+D13*'8. Pricing Summary'!$E$36+D14*'7. Custom Bespoke'!$E$26 | E19: =E11*'8. Pricing Summary'!$E$20+E12*'8. Pricing Summary'!$E$30+E13*'8. Pricing Summary'!$E$36+E14*'7. Custom Bespoke'!$E$26 | F19: =SUM(C19:E19) | G19: Tier1 agents × T1 + Tier2 × T2 + Tier3 × T3 + Custom × Custom
B22: C. Managed service revenue (recurring)
B23: Cumulative managed-service clients | C23: =C9*'1. Cover & Assumptions'!$C$51*0.5 | D23: =C9*'1. Cover & Assumptions'!$C$51 + D9*'1. Cover & Assumptions'!$C$51*0.5 | E23: =(C9+D9)*'1. Cover & Assumptions'!$C$51 + E9*'1. Cover & Assumptions'!$C$51*0.5 | G23: Avg paying clients during the year (half-year ramp for new ones).
B24: Managed service revenue | C24: =C23*'1. Cover & Assumptions'!$C$50*12 | D24: =D23*'1. Cover & Assumptions'!$C$50*12 | E24: =E23*'1. Cover & Assumptions'!$C$50*12 | F24: =SUM(C24:E24) | G24: Avg clients × ARPU × 12 months (managed service ARPU $12K/mo).
B27: D. Total revenue and split
B28: Item | C28: Year 1 | D28: Year 2 | E28: Year 3 | F28: 3-Year Total | G28: Notes
B29: Gross combined revenue (project + managed) | C29: =C19+C24 | D29: =D19+D24 | E29: =E19+E24 | F29: =SUM(C29:E29)
B30: AIdeology share (60% project + 60% managed) | C30: =C29*'1. Cover & Assumptions'!$C$39 | D30: =D29*'1. Cover & Assumptions'!$C$39 | E30: =E29*'1. Cover & Assumptions'!$C$39 | F30: =SUM(C30:E30)
B31: e& share (40% project + 40% managed; hosting separate) | C31: =C29*'1. Cover & Assumptions'!$C$40 | D31: =D29*'1. Cover & Assumptions'!$C$40 | E31: =E29*'1. Cover & Assumptions'!$C$40 | F31: =SUM(C31:E31)

Sheet 10. HPC RA Library
B2: HPC Reference Architecture Library — pre-prepared BoMs for vendor agility
B3: IN PLAIN ENGLISH: AIdeology has prepared NVIDIA-Certified reference architectures for every major OEM. When a Tier 3 deal lands, we pick the matching RA and produce a customer-specific BoM in days, not weeks.
B5: A. NVIDIA Enterprise RA families
B6: Family | C6: Pattern (C-G-N-B) | D6: GPU | E6: Default size (4-node SU) | F6: Max size | G6: Best fit
B7: Enterprise RA · RTX PRO | C7: 2-8-5-200 | D7: RTX PRO 6000 Blackwell SE | E7: 4 nodes / 32 GPUs | F7: 32 nodes / 256 GPUs | G7: Mid-density inference, agentic AI, fine-tuning at scale, dept-level GPUaaS
B8: HGX AI Factory | C8: 2-8-9-400 | D8: HGX H200 / B200 | E8: 4 nodes / 32 GPUs | F8: 128 nodes / 1,024 GPUs | G8: Workhorse training & fine-tuning, sovereign GPUaaS, regulated training jobs
B9: HGX B300 Single Plane | C9: 2-8-9-800 | D9: HGX B300 | E9: 4 nodes / 32 GPUs | F9: 32 nodes / 256 GPUs | G9: Frontier model training, advanced inference, AI factory build-out
B12: B. OEM-validated solutions (pre-prepared BoMs in hand)
B13: Vendor | C13: Solution | D13: Server | E13: GPU | F13: Pattern | G13: Size range | H13: Endorsements | I13: Notes
B14: Cisco | C14: Nexus Hyperfabric AI ERA | D14: UCS C885A Rack Server | E14: HGX H200 | F14: 2-8-9-400 → 2-8-10-400 | G14: 4 – 128 | H14: Infra · Spectrum-X · Networking | I14: Deep telco-network alignment with e&; preferred for sovereign GPUaaS.
B15: Cisco | C15: Nexus 9000 ERA | D15: UCS C885A Rack Server | E15: HGX H200 | F15: 2-8-9-400 | G15: 4 – 128 | H15: Infra · Spectrum-X · Networking | I15: Same UCS server, alternate fabric for existing Nexus 9000 customers.
B16: Cisco | C16: AI POD Infrastructure | D16: UCS C885A M8 | E16: HGX H200 | F16: 2-8-9-400 | G16: 4 – 16 | H16: Infra · Spectrum-X | I16: Smaller POD; ideal for first-deployment on-prem PoC or single-customer enterprise.
B17: Dell Technologies | C17: Dell AI Factory with NVIDIA | D17: PowerEdge XE7745 | E17: RTX PRO 6000 Blackwell SE / H200 NVL | F17: 2-8-5-200 | G17: 4, 16 | H17: Infra · Spectrum-X · Networking | I17: Strongest agentic AI reference. Mid-density inference workhorse.
B18: Dell Technologies | C18: Dell AI Factory with NVIDIA | D18: PowerEdge XE7740 | E18: RTX PRO 6000 Blackwell SE / H200 NVL | F18: 2-8-5-200 | G18: 4, 16 | H18: Infra · Spectrum-X · Networking | I18: Slightly different chassis; inference-leaning.
B19: Dell Technologies | C19: Dell AI Factory with NVIDIA | D19: PowerEdge XE9680 | E19: HGX H200 | F19: 2-8-9-400 | G19: 4, 12 | H19: Infra · Spectrum-X · Networking | I19: HGX-class training. Up to 12 SUs / 96 GPUs.
B20: Dell Federal | C20: Dell AI Factory for Government | D20: PowerEdge XE7740 / XE7745 | E20: RTX PRO 6000 Blackwell SE | F20: 2-8-5-200 | G20: 4 – 32 | H20: Infra · Spectrum-X | I20: Government-validated SKU; FedRAMP-aligned procurement.
B21: Lenovo | C21: Lenovo Hybrid AI 289 | D21: ThinkSystem SR680a V3 | E21: HGX B200 / H200 | F21: 2-8-9-400 | G21: 4 – 32 | H21: Infra · Spectrum-X · Networking | I21: Strong B200 path; co-engineered with NVIDIA on hybrid AI.
B22: Supermicro | C22: AI Factory · HGX | D22: SYS-A22GA-NBRT-G1 | E22: HGX B200 | F22: 2-8-9-400 | G22: 4 – 32 | H22: Infra · Spectrum-X | I22: Aggressive pricing on HGX class; favoured for fine-tune-heavy tenants.
B23: Supermicro | C23: AI Factory · RTX PRO 6000 | D23: SYS-522GA-NRT / SYS-422GL-NR / AS-5126GS-TNRT2 | E23: RTX PRO 6000 Blackwell SE | F23: 2-8-5-200 | G23: 4 – 32 | H23: Infra · Spectrum-X | I23: Mid-density inference; lowest TCO of RTX PRO RAs.
B24: Supermicro | C24: AI Factory · HGX B300 Single Plane | D24: SYS-822GS-NB3RT | E24: HGX B300 Single Plane | F24: 2-8-9-800 | G24: 4, 8, 32 | H24: Infra · Spectrum-X | I24: Frontier B300 — best for any new-flagship training opportunity.
B27: C. Indicative BoM list-price ranges (vendor MSRP — e& negotiating discount typically 20-35%)
B28: BoM size (GPUs) | C28: Pattern | D28: List-price range (USD) | E28: Indicative compute & storage | F28: AIdeology BoM coordination fee
B29: 32 GPUs · 4 nodes (1 SU) | C29: 2-8-5-200 (RTX PRO) | D29: $1.5M – $2.5M | E29: Mid-density inference + small fine-tune. ~250 TB AI storage. | F29: Included in Tier 3 Sheet 6
B30: 32 GPUs · 4 nodes (1 SU) | C30: 2-8-9-400 (HGX H200) | D30: $2.5M – $3.5M | E30: Training + fine-tune workhorse. ~500 TB AI storage. | F30: Included in Tier 3 Sheet 6
B31: 128 GPUs · 16 nodes (4 SUs) | C31: 2-8-5-200 (RTX PRO) | D31: $5M – $8M | E31: Departmental GPUaaS; multiple tenants. | F31: +$25K (allowance — Sheet 6)
B32: 256 GPUs · 32 nodes (8 SUs / Standard Pod) | C32: 2-8-9-400 (HGX H200/B200) | D32: $15M – $22M | E32: Standard fully-tested pod. Sovereign GPUaaS or flagship enterprise. | F32: +$50K (uplift)
B33: 1,024 GPUs · 128 nodes (32 SUs / Max Pod) | C33: 2-8-9-400 (HGX H200/B200) | D33: $60M – $90M | E33: Frontier-scale, multi-pod. Government / consortium build-out. | F33: +$150K (uplift)
B36: Reading guidance
B37: • AIdeology does not sell hardware — the OEM or e& takes that line. Our role is BoM coordination + integration, costed in Sheet 6.
B38: • For deals > 256 GPUs, AIdeology charges a BoM coordination uplift (column 6 above) on top of the standard Tier 3 cost stack.
B39: • Source: NVIDIA Enterprise Reference Architecture white paper — docs.nvidia.com/enterprise-reference-architectures.

Sheet 11. Sensitivity
B2: Sensitivity — Pipeline volume × tier mix × revenue split
B3: IN PLAIN ENGLISH: How does AIdeology's 3-year revenue change under different pipeline assumptions and revenue splits?
B5: A. Pipeline scenarios — 3-year deal volume
B6: Scenario | C6: Year 1 deals | D6: Year 2 deals | E6: Year 3 deals | F6: 3-Year Total | G6: Notes
B7: Low — slow ramp (3, 8, 15) | C7: 3 | D7: 8 | E7: 15 | F7: =SUM(C7:E7) | G7: Conservative: 3-8-15 deals. JSX low end.
B8: Mid — baseline (4, 11, 18) | C8: 4 | D8: 11 | E8: 18 | F8: =SUM(C8:E8) | G8: Baseline used in Sheet 9. JSX mid.
B9: High — strong adoption (8, 15, 25) | C9: 8 | D9: 15 | E9: 25 | F9: =SUM(C9:E9) | G9: Aggressive: 8-15-25 deals. JSX high end.
B12: B. Average revenue per deal (mix-weighted)
B13: Tier 1 avg agents per deal × T1 price + Tier 2 + Tier 3 + Custom | C13: ='1. Cover & Assumptions'!$C$45 * '1. Cover & Assumptions'!$C$49 * '8. Pricing Summary'!$E$20 + '1. Cover & Assumptions'!$C$46 * '8. Pricing Summary'!$E$30 + '1. Cover & Assumptions'!$C$47 * '8. Pricing Summary'!$E$36 + '1. Cover & Assumptions'!$C$48 * '7. Custom Bespoke'!$E$26 | G13: Single number = expected gross revenue per deal at current Tier mix.
B16: C. AIdeology 3-year revenue (USD) — Scenario × Revenue split
B17: Pipeline scenario | C17: 50/50 split | D17: 60/40 split (mid) | E17: 70/30 split | F17: Notes
B18: Low — slow ramp (3, 8, 15) | C18: =(F7*$C$13)*(1+0.3)*0.5 | D18: =(F7*$C$13)*(1+0.3)*0.6 | E18: =(F7*$C$13)*(1+0.3)*0.7 | G18: Total deals × avg revenue × (1 + 30% managed) × split %
B19: Mid — baseline (4, 11, 18) | C19: =(F8*$C$13)*(1+0.3)*0.5 | D19: =(F8*$C$13)*(1+0.3)*0.6 | E19: =(F8*$C$13)*(1+0.3)*0.7 | G19: Total deals × avg revenue × (1 + 30% managed) × split %
B20: High — strong adoption (8, 15, 25) | C20: =(F9*$C$13)*(1+0.3)*0.5 | D20: =(F9*$C$13)*(1+0.3)*0.6 | E20: =(F9*$C$13)*(1+0.3)*0.7 | G20: Total deals × avg revenue × (1 + 30% managed) × split %
B22: D. Tier mix sensitivity (per-deal revenue change)
B23: Mix scenario | C23: T1 % | D23: T2 % | E23: T3 % | F23: Avg revenue / deal
B24: Tier 1 heavy (small deals) | C24: 0.55 | D24: 0.3 | E24: 0.1 | F24: =C24*'1. Cover & Assumptions'!$C$49*'8. Pricing Summary'!$E$20 + D24*'8. Pricing Summary'!$E$30 + E24*'8. Pricing Summary'!$E$36 + 0.05*'7. Custom Bespoke'!$E$26
B25: Baseline | C25: 0.35 | D25: 0.45 | E25: 0.15 | F25: =C25*'1. Cover & Assumptions'!$C$49*'8. Pricing Summary'!$E$20 + D25*'8. Pricing Summary'!$E$30 + E25*'8. Pricing Summary'!$E$36 + 0.05*'7. Custom Bespoke'!$E$26
B26: Tier 3 heavy (flagships) | C26: 0.2 | D26: 0.4 | E26: 0.35 | F26: =C26*'1. Cover & Assumptions'!$C$49*'8. Pricing Summary'!$E$20 + D26*'8. Pricing Summary'!$E$30 + E26*'8. Pricing Summary'!$E$36 + 0.05*'7. Custom Bespoke'!$E$26
