Workbook

Sheet 0. Executive Summary
B2: AIdeology × e& — SMB Internal Pricing Summary
B3: One page. All the numbers that matter. Detail in tabs 1-10.
B5: A. WHAT ARE WE BUILDING?
B6: We build an AI platform for e& that lets small businesses subscribe to AI agents (Customer, Sales, Comms, Finance, Ops, People).
B7: v
B8: We earn money two ways: (1) fixed fees for building each wave, and (2) a % of every SMB subscription (revenue share) forever.
B10: B. WHAT DOES IT COST US?
B11: Wave 1 cost (platform + Customer Agent) | D11: Waves 2-4 cost (5 more agents) | F11: Total cost (all waves)
B12: ='7. Pricing Summary'!C11 -> 688572.5 | D12: ='6. Wave 2-4 Build Costs'!I22 -> 1262800 | F12: ='7. Pricing Summary'!C11+'6. Wave 2-4 Build Costs'!I22 -> 1951372.5
B14: C. WHAT DO WE CHARGE e&? (fixed fees)
B15: Wave 1 price to e& (40% margin) | D15: Waves 2-4 price to e& (45% margin) | F15: Total fixed-fee envelope
B16: ='7. Pricing Summary'!C13 -> 1147620.8 | D16: ='7. Pricing Summary'!E23 -> 2296000 | F16: ='7. Pricing Summary'!C29 -> 3443620.8
B17: Our margin on Wave 1: | C17: ='7. Pricing Summary'!C14 -> 0.4 | D17: Our margin on Waves 2-4: | E17: ='1. Cover & Assumptions'!C32 -> 0.45
B19: D. RECURRING REVENUE — our % of every SMB subscription
C20: Year 1 | D20: Year 2 | E20: Year 3 | F20: 3-Year Total
B21: Paying SMBs (avg) | C21: ='8. Revenue Share Model'!C8 -> 375 | D21: ='8. Revenue Share Model'!D8 -> 1500 | E21: ='8. Revenue Share Model'!E8 -> 3125
B22: e& gross revenue | C22: ='8. Revenue Share Model'!C10 -> 270000 | D22: ='8. Revenue Share Model'!D10 -> 1170000 | E22: ='8. Revenue Share Model'!E10 -> 2625000 | F22: =SUM(C22:E22) -> 4065000
B23: Our rev-share (15%) | C23: ='8. Revenue Share Model'!C12 -> 40500 | D23: ='8. Revenue Share Model'!D12 -> 175500 | E23: ='8. Revenue Share Model'!E12 -> 393750 | F23: =SUM(C23:E23) -> 609750
B26: E. TOTAL AIDEOLOGY REVENUE (3 years)
C27: Year 1 | D27: Year 2 | E27: Year 3 | F27: 3-Year Total
B28: Fixed fees (building) | C28: ='8. Revenue Share Model'!C22 -> 1629911.7 | D28: ='8. Revenue Share Model'!D22 -> 1394600 | E28: ='8. Revenue Share Model'!E22 -> 419109.09 | F28: =SUM(C28:E28) -> 3443620.8
B29: Rev-share (recurring) | C29: ='8. Revenue Share Model'!C12 -> 40500 | D29: ='8. Revenue Share Model'!D12 -> 175500 | E29: ='8. Revenue Share Model'!E12 -> 393750 | F29: =SUM(C29:E29) -> 609750
B30: TOTAL | C30: =SUM(C28:C29) -> 1670411.7 | D30: =SUM(D28:D29) -> 1570100 | E30: =SUM(E28:E29) -> 812859.09 | F30: =SUM(F28:F29) -> 4053370.8
B33: F. THREE WAYS TO PRICE THE DEAL
C34: Option A: Full price | D34: Option B: Hybrid | E34: Option C: Land & expand
B35: Up-front fee (Wave 1) | C35: ='7. Pricing Summary'!C13 -> 1147620.8 | D35: 500000 | E35: 250000
B36: Rev-share % | C36: 0.1 | D36: 0.18 | E36: 0.2
B37: Best for | C37: AIdeology cash flow | D37: Balanced risk/reward | E37: Easiest to sell
B38: Risk | C38: Hardest to close | D38: Moderate | E38: We lose money on Wave 1
B40: G. KEY RISK — our cost vs. what we proposed in the commercial framework
B41: The commercial framework we showed e& quoted $150K-$250K for the implementation. Our internal model shows it actually costs us $689K.
B42: If we charge $250K, we lose ~$439K on Wave 1. We need ~2.2 years of rev-share to break even. This is only viable if we believe in the subscriber ramp.
B43: Recommendation: negotiate a higher up-front fee ($500K+) OR a higher rev-share (18-20%) to protect our margins. See Sheet 7 for the three options.

Sheet 1. Cover & Assumptions
B2: AIdeology — Internal Pricing & Staffing Analysis
B3: e& B2B Acceleration · Pillar 01 — SMB Platform-Centric Agentic Solutions · v0.1 DRAFT
B4: INTERNAL — NOT FOR e&. Pricing model for AIdeology team only.
B5: Date: 2026-05-10
B7: How to use this workbook
B8: • All blue-text / yellow-shaded cells are editable inputs (rates, allocations, durations, margins, subscriber ramp).
B9: • All green-text cells are formulas linking other sheets — do not overwrite.
B10: • Sheet 2: Roles & Rates — adjust daily costs and bill rates here.
B11: • Sheet 3: Phase Staffing — Wave 1 (SMB Launch) headcount and allocation per phase.
B12: • Sheet 4: Phase Effort & Cost — calculated from staffing × rates.
B13: • Sheet 5: Other Costs — software, cloud, voice, WhatsApp BSP, contingency.
B14: • Sheet 6: Wave 2-4 Build Costs — Sales+Comms, Finance+Ops, People agentic solutions (incremental on top of platform).
... B22: Global assumptions
B23: Assumption | C23: Value | D23: Unit | E23: Notes / source
B24: Wave 1 (SMB Launch) duration | C24: 15 | D24: weeks | E24: Per launch plan: W1-15 covers M1 foundations → M6 GA + hypercare ramp.
B25: Working days per week | C25: 5 | D25: days | E25: Standard.
B26: Hours per working day | C26: 8 | D26: hours | E26: Standard.
B27: Currency | C27: USD | D27: — | E27: Internal model; final pricing to e& may be issued in AED or USD.
B28: FX assumption (USD→AED) | C28: 3.67 | D28: rate | E28: Pegged.
B29: AIdeology target gross margin (Wave 1 fixed fee) | C29: 0.4 | D29: % | E29: Higher than ADNOC: SMB platform is reusable IP; we own the blueprint stack.
B30: Contingency on direct cost | C30: 0.1 | D30: % | E30: Buffer for unknowns (sandbox slip, BSP approval delays, beta iteration).
B31: Risk reserve (held back) | C31: 0.05 | D31: % | E31: Held internally; not in price to e&.
B32: Wave 2-4 target gross margin (per-wave fee) | C32: 0.45 | D32: % | E32: Reusing platform — higher margin justified.
B33: Subscriber ramp — start month (after GA) | C33: 1 | D33: month | E33: Month 1 = first subscribers post GA. Cash-in starts Month 4 of programme.
B34: ARPU per SMB tenant (USD/month) | C34: 60 | D34: $/mo | E34: Per JSX commercial framework rev forecast ($60/mo blended).
B35: Rev-share % to AIdeology (mid) | C35: 0.15 | D35: % | E35: Range 10-20%, mid scenario 15%. Sensitivity sheet covers low/mid/high.
B36: Annual churn rate | C36: 0.2 | D36: % | E36: Net of upgrades. ~5%→3%/mo per JSX → ~20% annualised conservative.
B37: Rev-share term (years) | C37: 3 | D37: years | E37: Per JSX: 24-month minimum partnership, modelled to year 3.
B40: Important disclaimers
B41: • Daily rates in Sheet 2 are PLACEHOLDER values for AIdeology to validate against actual cost structure.
B42: • Headcount and allocation per phase are AIdeology's first-pass sizing. Adjust based on actual team capacity.
B43: • Wave 2-4 sizing in Sheet 6 assumes the base platform from Wave 1 is reused — only solution-layer work remains.
B44: • Subscriber ramp and churn in Sheet 8 are illustrative; replace with e& demand-model figures once available.
B45: • Voice (STT/TTS) and WhatsApp BSP costs are estimates pending vendor quotes (Deepgram, ElevenLabs, e& BSP).
B46: • Cloud cost depends on whether deployment is on e& OCI Dedicated Region / Azure CSP via e& / G42; revise once landing zone confirmed.

Sheet 2. Roles & Rates
B2: Roles & Daily Rates
B3: IN PLAIN ENGLISH: This is the team. 10 people with different skills. The 'Internal cost' column is what each person costs us per day. The 'Bill rate' is what we'd charge for them.
B5: Role | C5: Seniority | D5: Internal cost / day (USD) | E5: Bill rate / day (USD) | F5: Notes
B6: Engagement / Programme Manager | C6: Senior | D6: 1000 | E6: 1750 | F6: Single point of contact to e&; weekly governance; commercial owner.
B7: Solution Architect (Lead) | C7: Principal | D7: 1100 | E7: 2100 | F7: Owns reference architecture, multi-tenant design, latency budget, capability matrix.
B8: AI / LLM Engineer — Orchestration & Reasoning | C8: Senior | D8: 900 | E8: 1700 | F8: Agent graph, FSM, tool-calling, memory, guardrails, Portkey integration.
B9: Voice / Conversational Engineer | C9: Senior | D9: 850 | E9: 1650 | F9: Telephony (Toll Free 800), STT/TTS, WhatsApp/Web channels, Arabic/English NLP.
B10: Data & Integration Engineer | C10: Senior | D10: 900 | E10: 1550 | F10: Connectors (CRM, calendar, payments), e& billing API, vector store, knowledge ingestion.
B11: Frontend / UX Engineer | C11: Mid | D11: 750 | E11: 1300 | F11: Next.js tenant back office, onboarding, admin console, agent configuration UI.
B12: DevOps / Platform Engineer | C12: Senior | D12: 950 | E12: 1550 | F12: Helm/Terraform, CI/CD, multi-tenant K8s, observability stack, secrets, cost guardrails.
B13: QA Engineer | C13: Mid | D13: 700 | E13: 1200 | F13: Test packs, synthetic SMB data, automated regression, voice/chat acceptance tests.
B14: Security / Compliance Lead | C14: Senior | D14: 1050 | E14: 1750 | F14: Tenant isolation, NESA / TDRA / ADDA controls, pen-test coordination.
B15: Customer Success / Beta Ops Lead | C15: Mid | D15: 600 | E15: 950 | F15: Beta SMB recruitment & onboarding, feedback loops, runbooks, support escalation.
B17: Total roles in plan: 10

Sheet 3. Phase Staffing
B2: Wave 1 — Phase Staffing
B3: IN PLAIN ENGLISH: How many people work on each phase and how much of their time goes to this project. 15 weeks total, split into 6 phases. Scroll down to the yellow cells to change the numbers.
B5: Role | C5: P1 — Mobilisation & Foundations | D5: P2 — Platform Build & Customer Agent SDD | E5: P3 — Customer Agent Build | F5: P4 — Internal Alpha & Hardening | G5: P5 — Closed Beta & Production v1 | H5: P6 — GA Launch & Hypercare | I5: Total p-weeks
B6: Phase duration (weeks) | C6: 2 | D6: 3 | E6: 3 | F6: 2 | G6: 2 | H6: 3 | I6: —
B7: Engagement / Programme Manager | C7: =C22*C36*C6 -> 1 | D7: =D22*D36*D6 -> 1.8 | E7: =E22*E36*E6 -> 1.8 | F7: =F22*F36*F6 -> 1.4 | G7: =G22*G36*G6 -> 1.6 | H7: =H22*H36*H6 -> 1.8 | I7: =SUM(C7:H7) -> 9.4
B8: Solution Architect (Lead) | C8: =C23*C37*C6 -> 2 | D8: =D23*D37*D6 -> 3 | E8: =E23*E37*E6 -> 2.4 | F8: =F23*F37*F6 -> 1.2 | G8: =G23*G37*G6 -> 0.8 | H8: =H23*H37*H6 -> 0.9 | I8: =SUM(C8:H8) -> 10.3
B9: AI / LLM Engineer — Orchestration & Reasoning | C9: =C24*C38*C6 -> 1.2 | D9: =D24*D38*D6 -> 3 | E9: =E24*E38*E6 -> 6 | F9: =F24*F38*F6 -> 4 | G9: =G24*G38*G6 -> 1.4 | H9: =H24*H38*H6 -> 1.2 | I9: =SUM(C9:H9) -> 16.8
B10: Voice / Conversational Engineer | C10: =C25*C39*C6 -> 0.8 | D10: =D25*D39*D6 -> 2.4 | E10: =E25*E39*E6 -> 6 | F10: =F25*F39*F6 -> 2 | G10: =G25*G39*G6 -> 1.4 | H10: =H25*H39*H6 -> 0.9 | I10: =SUM(C10:H10) -> 13.5
B11: Data & Integration Engineer | C11: =C26*C40*C6 -> 1.2 | D11: =D26*D40*D6 -> 2.4 | E11: =E26*E40*E6 -> 3 | F11: =F26*F40*F6 -> 1.6 | G11: =G26*G40*G6 -> 1.2 | H11: =H26*H40*H6 -> 0.9 | I11: =SUM(C11:H11) -> 10.3
B12: Frontend / UX Engineer | C12: =C27*C41*C6 -> 1 | D12: =D27*D41*D6 -> 2.4 | E12: =E27*E41*E6 -> 3 | F12: =F27*F41*F6 -> 1.4 | G12: =G27*G41*G6 -> 1 | H12: =H27*H41*H6 -> 0.9 | I12: =SUM(C12:H12) -> 9.7
B13: DevOps / Platform Engineer | C13: =C28*C42*C6 -> 1.6 | D13: =D28*D42*D6 -> 6 | E13: =E28*E42*E6 -> 2.4 | F13: =F28*F42*F6 -> 1.6 | G13: =G28*G42*G6 -> 1.4 | H13: =H28*H42*H6 -> 1.5 | I13: =SUM(C13:H13) -> 14.5
B14: QA Engineer | C14: =C29*C43*C6 -> 0 | D14: =D29*D43*D6 -> 0 | E14: =E29*E43*E6 -> 1.5 | F14: =F29*F43*F6 -> 2 | G14: =G29*G43*G6 -> 4 | H14: =H29*H43*H6 -> 1.8 | I14: =SUM(C14:H14) -> 9.3
B15: Security / Compliance Lead | C15: =C30*C44*C6 -> 1 | D15: =D30*D44*D6 -> 1.5 | E15: =E30*E44*E6 -> 0.9 | F15: =F30*F44*F6 -> 1.2 | G15: =G30*G44*G6 -> 0.8 | H15: =H30*H44*H6 -> 0.6 | I15: =SUM(C15:H15) -> 6
B16: Customer Success / Beta Ops Lead | C16: =C31*C45*C6 -> 0 | D16: =D31*D45*D6 -> 0 | E16: =E31*E45*E6 -> 1.2 | F16: =F31*F45*F6 -> 1.2 | G16: =G31*G45*G6 -> 2 | H16: =H31*H45*H6 -> 2.1 | I16: =SUM(C16:H16) -> 6.5
B17: Total person-weeks per phase | C17: =SUM(C7:C16) -> 9.8 | D17: =SUM(D7:D16) -> 22.5 | E17: =SUM(E7:E16) -> 28.2 | F17: =SUM(F7:F16) -> 17.6 | G17: =SUM(G7:G16) -> 15.6 | H17: =SUM(H7:H16) -> 12.6 | I17: =SUM(C17:H17) -> 106.3
B19: EDITABLE — Headcount and Allocation % per Role per Phase
B20: Headcount per phase (number of people).
B21: Role | C21: P1 — Mobilisation & Foundations | D21: P2 — Platform Build & Customer Agent SDD | E21: P3 — Customer Agent Build | F21: P4 — Internal Alpha & Hardening | G21: P5 — Closed Beta & Production v1 | H21: P6 — GA Launch & Hypercare
B22: Engagement / Programme Manager | C22: 1 | D22: 1 | E22: 1 | F22: 1 | G22: 1 | H22: 1
B23: Solution Architect (Lead) | C23: 1 | D23: 1 | E23: 1 | F23: 1 | G23: 1 | H23: 1
B24: AI / LLM Engineer — Orchestration & Reasoning | C24: 1 | D24: 1 | E24: 2 | F24: 2 | G24: 1 | H24: 1
B25: Voice / Conversational Engineer | C25: 1 | D25: 1 | E25: 2 | F25: 1 | G25: 1 | H25: 1
B26: Data & Integration Engineer | C26: 1 | D26: 1 | E26: 1 | F26: 1 | G26: 1 | H26: 1
B27: Frontend / UX Engineer | C27: 1 | D27: 1 | E27: 1 | F27: 1 | G27: 1 | H27: 1
B28: DevOps / Platform Engineer | C28: 1 | D28: 2 | E28: 1 | F28: 1 | G28: 1 | H28: 1
B29: QA Engineer | C29: 0 | D29: 0 | E29: 1 | F29: 1 | G29: 2 | H29: 1
B30: Security / Compliance Lead | C30: 1 | D30: 1 | E30: 1 | F30: 1 | G30: 1 | H30: 1
B31: Customer Success / Beta Ops Lead | C31: 0 | D31: 0 | E31: 1 | F31: 1 | G31: 1 | H31: 1
B34: Allocation % per phase (share of time on this programme).
B35: Role | C35: P1 — Mobilisation & Foundations | D35: P2 — Platform Build & Customer Agent SDD | E35: P3 — Customer Agent Build | F35: P4 — Internal Alpha & Hardening | G35: P5 — Closed Beta & Production v1 | H35: P6 — GA Launch & Hypercare
B36: Engagement / Programme Manager | C36: 0.5 | D36: 0.6 | E36: 0.6 | F36: 0.7 | G36: 0.8 | H36: 0.6
B37: Solution Architect (Lead) | C37: 1 | D37: 1 | E37: 0.8 | F37: 0.6 | G37: 0.4 | H37: 0.3
B38: AI / LLM Engineer — Orchestration & Reasoning | C38: 0.6 | D38: 1 | E38: 1 | F38: 1 | G38: 0.7 | H38: 0.4
B39: Voice / Conversational Engineer | C39: 0.4 | D39: 0.8 | E39: 1 | F39: 1 | G39: 0.7 | H39: 0.3
B40: Data & Integration Engineer | C40: 0.6 | D40: 0.8 | E40: 1 | F40: 0.8 | G40: 0.6 | H40: 0.3
B41: Frontend / UX Engineer | C41: 0.5 | D41: 0.8 | E41: 1 | F41: 0.7 | G41: 0.5 | H41: 0.3
B42: DevOps / Platform Engineer | C42: 0.8 | D42: 1 | E42: 0.8 | F42: 0.8 | G42: 0.7 | H42: 0.5
B43: QA Engineer | C43: 0 | D43: 0 | E43: 0.5 | F43: 1 | G43: 1 | H43: 0.6
B44: Security / Compliance Lead | C44: 0.5 | D44: 0.5 | E44: 0.3 | F44: 0.6 | G44: 0.4 | H44: 0.2
B45: Customer Success / Beta Ops Lead | C45: 0 | D45: 0 | E45: 0.4 | F45: 0.6 | G45: 1 | H45: 0.7

Sheet 4. Phase Effort & Cost
B2: Wave 1 — What Does Each Person Cost Per Phase?
B3: IN PLAIN ENGLISH: This multiplies 'how long they work' (Sheet 3) × 'their daily rate' (Sheet 2). The total at the bottom is our people cost for Wave 1: ~$472K.
B5: INTERNAL COST (fully-loaded AIdeology cost)
B6: Role | C6: Cost / day | D6: P1 — Mobilisation & Foundations | E6: P2 — Platform Build & Customer Agent SDD | F6: P3 — Customer Agent Build | G6: P4 — Internal Alpha & Hardening | H6: P5 — Closed Beta & Production v1 | I6: P6 — GA Launch & Hypercare | J6: Total cost | K6: % of total
B7: Engagement / Programme Manager | C7: ='2. Roles & Rates'!D6 -> 1000 | D7: ='3. Phase Staffing'!C7*'1. Cover & Assumptions'!$C$25*$C7 -> 5000 | E7: ='3. Phase Staffing'!D7*'1. Cover & Assumptions'!$C$25*$C7 -> 9000 | F7: ='3. Phase Staffing'!E7*'1. Cover & Assumptions'!$C$25*$C7 -> 9000 | G7: ='3. Phase Staffing'!F7*'1. Cover & Assumptions'!$C$25*$C7 -> 7000 | H7: ='3. Phase Staffing'!G7*'1. Cover & Assumptions'!$C$25*$C7 -> 8000 | I7: ='3. Phase Staffing'!H7*'1. Cover & Assumptions'!$C$25*$C7 -> 9000 | J7: =SUM(D7:I7) -> 47000 | K7: =IFERROR(J7/$J$17,0) -> 0.099623761
B8: Solution Architect (Lead) | C8: ='2. Roles & Rates'!D7 -> 1100 | D8: ='3. Phase Staffing'!C8*'1. Cover & Assumptions'!$C$25*$C8 -> 11000 | E8: ='3. Phase Staffing'!D8*'1. Cover & Assumptions'!$C$25*$C8 -> 16500 | F8: ='3. Phase Staffing'!E8*'1. Cover & Assumptions'!$C$25*$C8 -> 13200 | G8: ='3. Phase Staffing'!F8*'1. Cover & Assumptions'!$C$25*$C8 -> 6600 | H8: ='3. Phase Staffing'!G8*'1. Cover & Assumptions'!$C$25*$C8 -> 4400 | I8: ='3. Phase Staffing'!H8*'1. Cover & Assumptions'!$C$25*$C8 -> 4950 | J8: =SUM(D8:I8) -> 56650 | K8: =IFERROR(J8/$J$17,0) -> 0.12007843
B9: AI / LLM Engineer — Orchestration & Reasoning | C9: ='2. Roles & Rates'!D8 -> 900 | D9: ='3. Phase Staffing'!C9*'1. Cover & Assumptions'!$C$25*$C9 -> 5400 | E9: ='3. Phase Staffing'!D9*'1. Cover & Assumptions'!$C$25*$C9 -> 13500 | F9: ='3. Phase Staffing'!E9*'1. Cover & Assumptions'!$C$25*$C9 -> 27000 | G9: ='3. Phase Staffing'!F9*'1. Cover & Assumptions'!$C$25*$C9 -> 18000 | H9: ='3. Phase Staffing'!G9*'1. Cover & Assumptions'!$C$25*$C9 -> 6300 | I9: ='3. Phase Staffing'!H9*'1. Cover & Assumptions'!$C$25*$C9 -> 5400 | J9: =SUM(D9:I9) -> 75600 | K9: =IFERROR(J9/$J$17,0) -> 0.16024588
B10: Voice / Conversational Engineer | C10: ='2. Roles & Rates'!D9 -> 850 | D10: ='3. Phase Staffing'!C10*'1. Cover & Assumptions'!$C$25*$C10 -> 3400 | E10: ='3. Phase Staffing'!D10*'1. Cover & Assumptions'!$C$25*$C10 -> 10200 | F10: ='3. Phase Staffing'!E10*'1. Cover & Assumptions'!$C$25*$C10 -> 25500 | G10: ='3. Phase Staffing'!F10*'1. Cover & Assumptions'!$C$25*$C10 -> 8500 | H10: ='3. Phase Staffing'!G10*'1. Cover & Assumptions'!$C$25*$C10 -> 5950 | I10: ='3. Phase Staffing'!H10*'1. Cover & Assumptions'!$C$25*$C10 -> 3825 | J10: =SUM(D10:I10) -> 57375 | K10: =IFERROR(J10/$J$17,0) -> 0.12161518
B11: Data & Integration Engineer | C11: ='2. Roles & Rates'!D10 -> 900 | D11: ='3. Phase Staffing'!C11*'1. Cover & Assumptions'!$C$25*$C11 -> 5400 | E11: ='3. Phase Staffing'!D11*'1. Cover & Assumptions'!$C$25*$C11 -> 10800 | F11: ='3. Phase Staffing'!E11*'1. Cover & Assumptions'!$C$25*$C11 -> 13500 | G11: ='3. Phase Staffing'!F11*'1. Cover & Assumptions'!$C$25*$C11 -> 7200 | H11: ='3. Phase Staffing'!G11*'1. Cover & Assumptions'!$C$25*$C11 -> 5400 | I11: ='3. Phase Staffing'!H11*'1. Cover & Assumptions'!$C$25*$C11 -> 4050 | J11: =SUM(D11:I11) -> 46350 | K11: =IFERROR(J11/$J$17,0) -> 0.098245986
B12: Frontend / UX Engineer | C12: ='2. Roles & Rates'!D11 -> 750 | D12: ='3. Phase Staffing'!C12*'1. Cover & Assumptions'!$C$25*$C12 -> 3750 | E12: ='3. Phase Staffing'!D12*'1. Cover & Assumptions'!$C$25*$C12 -> 9000 | F12: ='3. Phase Staffing'!E12*'1. Cover & Assumptions'!$C$25*$C12 -> 11250 | G12: ='3. Phase Staffing'!F12*'1. Cover & Assumptions'!$C$25*$C12 -> 5250 | H12: ='3. Phase Staffing'!G12*'1. Cover & Assumptions'!$C$25*$C12 -> 3750 | I12: ='3. Phase Staffing'!H12*'1. Cover & Assumptions'!$C$25*$C12 -> 3375 | J12: =SUM(D12:I12) -> 36375 | K12: =IFERROR(J12/$J$17,0) -> 0.077102432
B13: DevOps / Platform Engineer | C13: ='2. Roles & Rates'!D12 -> 950 | D13: ='3. Phase Staffing'!C13*'1. Cover & Assumptions'!$C$25*$C13 -> 7600 | E13: ='3. Phase Staffing'!D13*'1. Cover & Assumptions'!$C$25*$C13 -> 28500 | F13: ='3. Phase Staffing'!E13*'1. Cover & Assumptions'!$C$25*$C13 -> 11400 | G13: ='3. Phase Staffing'!F13*'1. Cover & Assumptions'!$C$25*$C13 -> 7600 | H13: ='3. Phase Staffing'!G13*'1. Cover & Assumptions'!$C$25*$C13 -> 6650 | I13: ='3. Phase Staffing'!H13*'1. Cover & Assumptions'!$C$25*$C13 -> 7125 | J13: =SUM(D13:I13) -> 68875 | K13: =IFERROR(J13/$J$17,0) -> 0.1459912
B14: QA Engineer | C14: ='2. Roles & Rates'!D13 -> 700 | D14: ='3. Phase Staffing'!C14*'1. Cover & Assumptions'!$C$25*$C14 -> 0 | E14: ='3. Phase Staffing'!D14*'1. Cover & Assumptions'!$C$25*$C14 -> 0 | F14: ='3. Phase Staffing'!E14*'1. Cover & Assumptions'!$C$25*$C14 -> 5250 | G14: ='3. Phase Staffing'!F14*'1. Cover & Assumptions'!$C$25*$C14 -> 7000 | H14: ='3. Phase Staffing'!G14*'1. Cover & Assumptions'!$C$25*$C14 -> 14000 | I14: ='3. Phase Staffing'!H14*'1. Cover & Assumptions'!$C$25*$C14 -> 6300 | J14: =SUM(D14:I14) -> 32550 | K14: =IFERROR(J14/$J$17,0) -> 0.068994754
B15: Security / Compliance Lead | C15: ='2. Roles & Rates'!D14 -> 1050 | D15: ='3. Phase Staffing'!C15*'1. Cover & Assumptions'!$C$25*$C15 -> 5250 | E15: ='3. Phase Staffing'!D15*'1. Cover & Assumptions'!$C$25*$C15 -> 7875 | F15: ='3. Phase Staffing'!E15*'1. Cover & Assumptions'!$C$25*$C15 -> 4725 | G15: ='3. Phase Staffing'!F15*'1. Cover & Assumptions'!$C$25*$C15 -> 6300 | H15: ='3. Phase Staffing'!G15*'1. Cover & Assumptions'!$C$25*$C15 -> 4200 | I15: ='3. Phase Staffing'!H15*'1. Cover & Assumptions'!$C$25*$C15 -> 3150 | J15: =SUM(D15:I15) -> 31500 | K15: =IFERROR(J15/$J$17,0) -> 0.066769117
B16: Customer Success / Beta Ops Lead | C16: ='2. Roles & Rates'!D15 -> 600 | D16: ='3. Phase Staffing'!C16*'1. Cover & Assumptions'!$C$25*$C16 -> 0 | E16: ='3. Phase Staffing'!D16*'1. Cover & Assumptions'!$C$25*$C16 -> 0 | F16: ='3. Phase Staffing'!E16*'1. Cover & Assumptions'!$C$25*$C16 -> 3600 | G16: ='3. Phase Staffing'!F16*'1. Cover & Assumptions'!$C$25*$C16 -> 3600 | H16: ='3. Phase Staffing'!G16*'1. Cover & Assumptions'!$C$25*$C16 -> 6000 | I16: ='3. Phase Staffing'!H16*'1. Cover & Assumptions'!$C$25*$C16 -> 6300 | J16: =SUM(D16:I16) -> 19500 | K16: =IFERROR(J16/$J$17,0) -> 0.041333263
B17: Total internal cost per phase | D17: =SUM(D7:D16) -> 46800 | E17: =SUM(E7:E16) -> 105375 | F17: =SUM(F7:F16) -> 124425 | G17: =SUM(G7:G16) -> 77050 | H17: =SUM(H7:H16) -> 64650 | I17: =SUM(I7:I16) -> 53475 | J17: =SUM(J7:J16) -> 471775 | K17: 100%

Sheet 5. Other Costs
B2: Wave 1 — Non-People Costs (software, cloud, travel, etc.)
B3: IN PLAIN ENGLISH: Everything we spend that isn't salaries — cloud servers, AI APIs, WhatsApp, security tools, flights to the UAE, etc. Total: ~$154K.
B5: Cost item | C5: Unit cost | D5: Quantity / months | E5: Total cost | F5: Phase trigger | G5: Notes
B6: Cloud / K8s dev + staging cluster (e& OCI / Azure CSP) | C6: 6000 | D6: 4 | E6: =C6*D6 -> 24000 | F6: P1–P6 | G6: Multi-tenant cluster footprint during build & beta. Production sized separately.
B7: LLM Gateway licence (Portkey / equivalent) | C7: 1500 | D7: 4 | E7: =C7*D7 -> 6000 | F7: P1–P6 | G7: Routing, fallback, observability, cost guardrails across Azure OpenAI / Anthropic / OpenInnovation.
B8: LLM API spend — build, alpha, beta | C8: 4000 | D8: 4 | E8: =C8*D8 -> 16000 | F8: P2–P6 | G8: Includes prompt engineering, regression test runs, beta tenant traffic.
B9: STT / TTS API (Deepgram, ElevenLabs / Azure Speech) | C9: 2500 | D9: 4 | E9: =C9*D9 -> 10000 | F9: P2–P6 | G9: Voice agent training & beta. Arabic/English, low-latency.
B10: WhatsApp BSP (e& or partner) — sandbox + tests | C10: 1500 | D10: 4 | E10: =C10*D10 -> 6000 | F10: P2–P6 | G10: Template approval, opt-in flows, message-rate tests on UAE numbers.
B11: Observability stack (Grafana Cloud, Loki, Langfuse) | C11: 1500 | D11: 4 | E11: =C11*D11 -> 6000 | F11: P1–P6 | G11: Hosted observability for the AIdeology team; production stack runs in e& env.
B12: CI/CD & repo hosting (GitHub Enterprise) | C12: 800 | D12: 4 | E12: =C12*D12 -> 3200 | F12: P1–P6 | G12: Pipelines, secrets, environments, security scanning.
B13: Security tooling (SAST/DAST/SCA — Snyk / Checkmarx) | C13: 2000 | D13: 4 | E13: =C13*D13 -> 8000 | F13: P1–P6 | G13: Continuous static & dependency scanning.
B14: Pen-test (third-party, before GA) | C14: 25000 | D14: 1 | E14: =C14*D14 -> 25000 | F14: P5 | G14: External pen-test prior to GA; required for production launch.
B15: Travel — UAE (3 people × 5 days × 4 trips) | C15: 9000 | D15: 4 | E15: =C15*D15 -> 36000 | F15: P1–P6 | G15: On-site mobilisation, integration, beta kickoff, GA launch.
B16: Marketing / launch event support | C16: 8000 | D16: 1 | E16: =C16*D16 -> 8000 | F16: P6 | G16: GA launch enablement: collateral, demo videos, launch event support.
B17: Misc (printing, demos, contingency petty) | C17: 1500 | D17: 4 | E17: =C17*D17 -> 6000 | F17: All | G17: Petty cash for the engagement.
B18: Total other costs (subtotal) | E18: =SUM(E6:E17) -> 154200

Sheet 6. Wave 2-4 Build Costs
B2: Waves 2-4 — Cost of the Next 5 Agents
B3: IN PLAIN ENGLISH: After Wave 1, we build 5 more agents (Sales, Comms, Finance, Ops, People). The platform already exists, so each one is cheaper. This sheet shows the cost of each.
B5: Role | C5: Cost / day | D5: Wave 2A — Sales Agent (CRM, lead, pipeline) | E5: Wave 2B — Comms Hub (omnichannel inbox, campaigns) | F5: Wave 3A — Finance Agent (invoicing, VAT, e& Pay) | G5: Wave 3B — Ops Agent (tasks, SOP KB, service desk) | H5: Wave 4 — People Agent (WPS, payroll, HR) | I5: Total p-weeks (×days) | J5: Notes
B6: Engagement / Programme Manager | C6: ='2. Roles & Rates'!D6 -> 1000 | D6: 3 | E6: 3 | F6: 3 | G6: 3 | H6: 3 | I6: =SUM(D6:H6) -> 15 | J6: Engagement coordination; lighter than Wave 1.
B7: Solution Architect (Lead) | C7: ='2. Roles & Rates'!D7 -> 1100 | D7: 4 | E7: 4 | F7: 4 | G7: 4 | H7: 3 | I7: =SUM(D7:H7) -> 19 | J7: Solution architect supports SDD spec & integration design per wave.
B8: AI / LLM Engineer — Orchestration & Reasoning | C8: ='2. Roles & Rates'!D8 -> 900 | D8: 10 | E8: 8 | F8: 8 | G8: 8 | H8: 6 | I8: =SUM(D8:H8) -> 40 | J8: Heaviest role per agent — orchestration, prompts, tools, evals.
B9: Voice / Conversational Engineer | C9: ='2. Roles & Rates'!D9 -> 850 | D9: 4 | E9: 8 | F9: 2 | G9: 2 | H9: 0 | I9: =SUM(D9:H9) -> 16 | J9: Comms Hub = heaviest voice; Sales = light voice; Finance/Ops = minimal voice; People = none.
B10: Data & Integration Engineer | C10: ='2. Roles & Rates'!D10 -> 900 | D10: 10 | E10: 8 | F10: 12 | G10: 8 | H10: 10 | I10: =SUM(D10:H10) -> 48 | J10: Connectors are wave-driver: Finance APIs, HR systems, tax. Most variable.
B11: Frontend / UX Engineer | C11: ='2. Roles & Rates'!D11 -> 750 | D11: 6 | E11: 6 | F11: 6 | G11: 6 | H11: 6 | I11: =SUM(D11:H11) -> 30 | J11: Tenant UI tweaks per agent + admin console.
B12: DevOps / Platform Engineer | C12: ='2. Roles & Rates'!D12 -> 950 | D12: 3 | E12: 3 | F12: 3 | G12: 3 | H12: 3 | I12: =SUM(D12:H12) -> 15 | J12: Per-wave deployment, observability hooks, cost guardrails.
B13: QA Engineer | C13: ='2. Roles & Rates'!D13 -> 700 | D13: 4 | E13: 4 | F13: 4 | G13: 4 | H13: 4 | I13: =SUM(D13:H13) -> 20 | J13: Test packs, regression, acceptance.
B14: Security / Compliance Lead | C14: ='2. Roles & Rates'!D14 -> 1050 | D14: 3 | E14: 3 | F14: 4 | G14: 3 | H14: 4 | I14: =SUM(D14:H14) -> 17 | J14: Higher for Finance & People (PII, payroll regs).
B15: Customer Success / Beta Ops Lead | C15: ='2. Roles & Rates'!D15 -> 600 | D15: 3 | E15: 3 | F15: 3 | G15: 3 | H15: 3 | I15: =SUM(D15:H15) -> 15 | J15: Pilot tenant onboarding & support per wave.
B16: Total person-weeks per wave | D16: =SUM(D6:D15) -> 50 | E16: =SUM(E6:E15) -> 50 | F16: =SUM(F6:F15) -> 49 | G16: =SUM(G6:G15) -> 44 | H16: =SUM(H6:H15) -> 42 | I16: =SUM(I6:I15) -> 235
B18: Personnel cost per wave (USD)
B19: Item | C19: Wave 2A — Sales Agent (CRM, lead, pipeline) | D19: Wave 2B — Comms Hub (omnichannel inbox, campaigns) | E19: Wave 3A — Finance Agent (invoicing, VAT, e& Pay) | F19: Wave 3B — Ops Agent (tasks, SOP KB, service desk) | G19: Wave 4 — People Agent (WPS, payroll, HR) | H19: Total
B20: Personnel cost | D20: =(D6*$C6+D7*$C7+D8*$C8+D9*$C9+D10*$C10+D11*$C11+D12*$C12+D13*$C13+D14*$C14+D15*$C15)*'1. Cover & Assumptions'!$C$25 -> 219500 | E20: =(E6*$C6+E7*$C7+E8*$C8+E9*$C9+E10*$C10+E11*$C11+E12*$C12+E13*$C13+E14*$C14+E15*$C15)*'1. Cover & Assumptions'!$C$25 -> 218500 | F20: =(F6*$C6+F7*$C7+F8*$C8+F9*$C9+F10*$C10+F11*$C11+F12*$C12+F13*$C13+F14*$C14+F15*$C15)*'1. Cover & Assumptions'!$C$25 -> 216250 | G20: =(G6*$C6+G7*$C7+G8*$C8+G9*$C9+G10*$C10+G11*$C11+G12*$C12+G13*$C13+G14*$C14+G15*$C15)*'1. Cover & Assumptions'!$C$25 -> 193000 | H20: =(H6*$C6+H7*$C7+H8*$C8+H9*$C9+H10*$C10+H11*$C11+H12*$C12+H13*$C13+H14*$C14+H15*$C15)*'1. Cover & Assumptions'!$C$25 -> 184250 | I20: =SUM(D20:H20) -> 1031500
B21: Other costs (per wave, ~30% of Wave 1 envelope) | D21: ='5. Other Costs'!$E$18*0.3 -> 46260 | E21: ='5. Other Costs'!$E$18*0.3 -> 46260 | F21: ='5. Other Costs'!$E$18*0.3 -> 46260 | G21: ='5. Other Costs'!$E$18*0.3 -> 46260 | H21: ='5. Other Costs'!$E$18*0.3 -> 46260 | I21: =SUM(D21:H21) -> 231300
B22: Total fully-loaded cost per wave | D22: =D20+D21 -> 265760 | E22: =E20+E21 -> 264760 | F22: =F20+F21 -> 262510 | G22: =G20+G21 -> 239260 | H22: =H20+H21 -> 230510 | I22: =SUM(D22:H22) -> 1262800

Sheet 7. Pricing Summary
B2: Pricing Summary — What We Charge e&
B3: IN PLAIN ENGLISH: Takes our costs, adds a safety buffer (10%) and our profit margin (40%), and gives us the price we should charge e& for each wave.
B5: Wave 1 — SMB Launch (Base Platform + Customer Agent)
B6: Component | C6: Value (USD) | E6: Notes
B7: Personnel cost — internal (sum of 6 phases) | C7: ='4. Phase Effort & Cost'!$J$17 -> 471775 | E7: From Sheet 4 (cost basis).
B8: Other costs — non-personnel | C8: ='5. Other Costs'!$E$18 -> 154200 | E8: From Sheet 5.
B9: Subtotal — direct cost | C9: =C7+C8 -> 625975 | E9: Personnel + non-personnel.
B10: Contingency on direct cost | C10: =C9*'1. Cover & Assumptions'!$C$30 -> 62597.5 | E10: % from Sheet 1.
B11: Total fully-loaded cost | C11: =C9+C10 -> 688572.5 | E11: Direct cost + contingency.
B12: AIdeology margin on cost (grossed up) | C12: =C11/(1-'1. Cover & Assumptions'!$C$29)-C11 -> 459048.33 | E12: Margin grossed up: price = cost / (1 - margin).
B13: Price to e& — Wave 1 (Implementation Fee) | C13: =C11+C12 -> 1147620.8 | E13: Fixed-fee proposed for Wave 1.
B14: Effective margin % | C14: =IFERROR((C13-C11)/C13,0) -> 0.4 | E14: Should approximate target margin from Sheet 1.
B16: Waves 2-4 — Per-Wave Pricing (Solution-layer only)
B17: Wave | C17: Total cost (USD) | D17: Margin (USD) | E17: Price to e& (USD)
B18: Wave 2A — Sales Agent | C18: ='6. Wave 2-4 Build Costs'!D22 -> 265760 | D18: =C18/(1-'1. Cover & Assumptions'!$C$32)-C18 -> 217440 | E18: =C18+D18 -> 483200
B19: Wave 2B — Comms Hub | C19: ='6. Wave 2-4 Build Costs'!E22 -> 264760 | D19: =C19/(1-'1. Cover & Assumptions'!$C$32)-C19 -> 216621.82 | E19: =C19+D19 -> 481381.82
B20: Wave 3A — Finance Agent | C20: ='6. Wave 2-4 Build Costs'!F22 -> 262510 | D20: =C20/(1-'1. Cover & Assumptions'!$C$32)-C20 -> 214780.91 | E20: =C20+D20 -> 477290.91
B21: Wave 3B — Ops Agent | C21: ='6. Wave 2-4 Build Costs'!G22 -> 239260 | D21: =C21/(1-'1. Cover & Assumptions'!$C$32)-C21 -> 195758.18 | E21: =C21+D21 -> 435018.18
B22: Wave 4 — People Agent | C22: ='6. Wave 2-4 Build Costs'!H22 -> 230510 | D22: =C22/(1-'1. Cover & Assumptions'!$C$32)-C22 -> 188599.09 | E22: =C22+D22 -> 419109.09
B23: Total Waves 2-4 (5 agents) | C23: =SUM(C18:C22) -> 1262800 | D23: =SUM(D18:D22) -> 1033200 | E23: =SUM(E18:E22) -> 2296000
B25: Programme envelope (Wave 1 + Waves 2-4)
B26: Component | C26: Value (USD) | E26: Notes
B27: Wave 1 — Implementation fixed fee | C27: =C13 -> 1147620.8 | E27: From Wave 1 stack above.
B28: Waves 2-4 — Solution build fees (5 agents) | C28: =E23 -> 2296000 | E28: Sum of Wave 2A/2B/3A/3B/4.
B29: Total fixed-fee envelope | C29: =C27+C28 -> 3443620.8 | E29: All implementation & build fees.
B30: Risk reserve (held internally — not in price) | C30: =C11*'1. Cover & Assumptions'!$C$31 -> 34428.625 | E30: Held at AIdeology level for genuine Wave-1 risk events.
B33: Reality check — internal cost vs JSX commercial framework
B34: Reference / scenario | C34: Value (USD) | E34: Notes
B35: Internal Wave 1 price (this model, 40% margin) | C35: =C13 -> 1147620.8 | E35: What we should charge to hit target margin.
B36: JSX proposed implementation fee — low end | C36: 150000 | E36: Per current commercial framework: low end $150K (under our cost).
B37: JSX proposed implementation fee — high end | C37: 250000 | E37: Per current commercial framework: high end $250K (still under our cost).
B38: Gap vs our cost (low-end JSX) | C38: =C36-'7. Pricing Summary'!$C$11 -> -538572.5 | E38: Loss on Wave 1 if we sell at $150K.
B39: Gap vs our cost (high-end JSX) | C39: =C37-'7. Pricing Summary'!$C$11 -> -438572.5 | E39: Loss on Wave 1 if we sell at $250K.
B40: Years of rev-share needed to break even (high-end JSX, mid adoption) | C40: =IFERROR(('7. Pricing Summary'!$C$11-C37)/(('8. Revenue Share Model'!$C$12+'8. Revenue Share Model'!$D$12+'8. Revenue Share Model'!$E$12)/3),0) -> 2.1577983 | E40: Wave 1 cost gap ÷ avg annual rev-share (Y1-Y3 mid). Indicative: rev-share ramps so payback is faster in later years.
B43: Recommended commercial structures (3 options)
B44: Option | C44: Up-front fee | D44: Rev-share % | E44: Notes
B45: A — Cost-plus (full margin up-front) | C45: =C13 -> 1147620.8 | D45: 0.1 | E45: Charge full implementation fee. Rev-share at 10% (low end). Best for AIdeology cash-flow but hardest to sell.
B46: B — Hybrid (split) | C46: 500000 | D46: 0.18 | E46: Up-front fee covers core platform cost; aggressive rev-share captures upside. Balanced.
B47: C — Land & expand (JSX framework) | C47: 250000 | D47: 0.2 | E47: Aggressive sell-in at $250K + 20% rev-share. Needs subscriber ramp + Wave 2-4 fees to recover Wave 1 cost.

Sheet 8. Revenue Share Model
B2: Revenue Share — Our Recurring Income
B3: IN PLAIN ENGLISH: Every month, SMBs pay e& a subscription. We get 15% of that. As more SMBs sign up, this grows every year. This is the long-term prize on top of the fixed fees.
B5: Subscriber ramp (paying SMB tenants — end of year)
B6: Metric | C6: Year 1 | D6: Year 2 | E6: Year 3 | F6: Notes
B7: Paying SMB tenants — end of year (mid) | C7: 750 | D7: 2250 | E7: 4000 | F7: Per JSX: 500-1,000 Y1, 1,500-3,000 Y2, 3,000-5,000+ Y3 (mid points).
B8: Avg paying tenants over the year (mid) | C8: 375 | D8: 1500 | E8: 3125 | F8: Linear ramp assumption. Override if e& demand model differs.
B9: ARPU per tenant (USD/month) | C9: 60 | D9: 65 | E9: 70 | F9: Mild upgrade assumption (cross-sell from Customer to Sales/Comms agents).
B10: Gross subscription revenue (USD/year) | C10: =C8*C9*12 -> 270000 | D10: =D8*D9*12 -> 1170000 | E10: =E8*E9*12 -> 2625000 | F10: Avg tenants × ARPU × 12 months. e& top-line.
B11: Rev-share % to AIdeology (mid) | C11: ='1. Cover & Assumptions'!$C$35 -> 0.15 | D11: ='1. Cover & Assumptions'!$C$35 -> 0.15 | E11: ='1. Cover & Assumptions'!$C$35 -> 0.15 | F11: Sourced from Sheet 1 input (override per year if degressive tiers apply).
B12: AIdeology rev-share revenue (USD/year) | C12: =C10*C11 -> 40500 | D12: =D10*D11 -> 175500 | E12: =E10*E11 -> 393750
B14: Implementation & wave fees (recognised by year)
B15: Item | C15: Year 1 | D15: Year 2 | E15: Year 3 | F15: Notes
B16: Wave 1 implementation fee | C16: ='7. Pricing Summary'!$C$13 -> 1147620.8 | D16: 0 | E16: 0 | F16: Recognised in Y1 across milestones.
B17: Wave 2A — Sales Agent (50/50 Y1/Y2) | C17: =0.5*'7. Pricing Summary'!$E$18 -> 241600 | D17: =0.5*'7. Pricing Summary'!$E$18 -> 241600 | E17: 0 | F17: Wave 2 kicks off ~M9, finishes M16.
B18: Wave 2B — Comms Hub (50/50 Y1/Y2) | C18: =0.5*'7. Pricing Summary'!$E$19 -> 240690.91 | D18: =0.5*'7. Pricing Summary'!$E$19 -> 240690.91 | E18: 0
B19: Wave 3A — Finance Agent (Y2) | C19: 0 | D19: ='7. Pricing Summary'!$E$20 -> 477290.91 | E19: 0 | F19: Built in Y2.
B20: Wave 3B — Ops Agent (Y2) | C20: 0 | D20: ='7. Pricing Summary'!$E$21 -> 435018.18 | E20: 0
B21: Wave 4 — People Agent (Y3) | C21: 0 | D21: 0 | E21: ='7. Pricing Summary'!$E$22 -> 419109.09 | F21: Built in Y3.
B22: Subtotal — fees recognised | C22: =SUM(C16:C21) -> 1629911.7 | D22: =SUM(D16:D21) -> 1394600 | E22: =SUM(E16:E21) -> 419109.09
B24: AIdeology total revenue (rev-share + fees)
B25: Item | C25: Year 1 | D25: Year 2 | E25: Year 3 | F25: 3-Year Total
B26: Rev-share revenue | C26: =C12 -> 40500 | D26: =D12 -> 175500 | E26: =E12 -> 393750 | F26: =SUM(C26:E26) -> 609750
B27: Implementation & wave fees | C27: =C22 -> 1629911.7 | D27: =D22 -> 1394600 | E27: =E22 -> 419109.09 | F27: =SUM(C27:E27) -> 3443620.8
B28: Total AIdeology revenue | C28: =SUM(C26:C27) -> 1670411.7 | D28: =SUM(D26:D27) -> 1570100 | E28: =SUM(E26:E27) -> 812859.09 | F28: =SUM(C28:E28) -> 4053370.8

Sheet 9. Payment Milestones
B2: Wave 1 — When Does e& Pay Us?
B3: IN PLAIN ENGLISH: e& pays us in 4 instalments, each triggered by a milestone (kickoff, alpha, beta, launch). This also shows our cash-flow: when money comes in vs when we spend it.
B5: # | C5: Milestone / trigger | D5: % of price | E5: Target week | F5: Amount (USD) | G5: Acceptance criteria
B6: 1 | C6: Mobilisation & SOW signature (kickoff) | D6: 0.25 | E6: T + 0 | F6: =D6*'7. Pricing Summary'!$C$13 -> 286905.21 | G6: M1 — Platform foundations stood up; team mobilised within 48h; SOW Schedule A traceability accepted.
B7: 2 | C7: Customer Agent in dev + Internal Alpha | D7: 0.25 | E7: T + 6 wk | F7: =D7*'7. Pricing Summary'!$C$13 -> 286905.21 | G7: M2 + M3 — Voice/WhatsApp/web flows working end-to-end; alpha used by AIdeology + e& staff.
B8: 3 | C8: Closed beta live (10–20 SMBs) | D8: 0.3 | E8: T + 9 wk | F8: =D8*'7. Pricing Summary'!$C$13 -> 344286.25 | G8: M4 — Beta tenants in production; CSAT and CAC data flowing; escalation paths validated.
B9: 4 | C9: GA launch + Wave-2 readiness | D9: 0.2 | E9: T + 13–15 wk | F9: =D9*'7. Pricing Summary'!$C$13 -> 229524.17 | G9: M5 + M6 — Production v1 hardened; security + Arabic/English acceptance tests passed; marketplace open.
C10: Sum check | D10: =SUM(D6:D9) -> 1 | F10: =SUM(F6:F9) -> 1147620.8
B13: Indicative monthly cash-flow — Wave 1 only (months from kickoff)
B14: Item | C14: M0 (kickoff) | D14: M1 | E14: M2 | F14: M3 (beta) | G14: M4 (GA)
B15: Cash IN (payments from e&) | C15: =F6 -> 286905.21 | D15: 0 | E15: =F7 -> 286905.21 | F15: =F8 -> 344286.25 | G15: =F9 -> 229524.17
B16: Cash OUT (AIdeology cost burn, est.) | C16: ='4. Phase Effort & Cost'!D17*0.5+'5. Other Costs'!$E$18*0.1 -> 38820 | D16: ='4. Phase Effort & Cost'!D17*0.5+'4. Phase Effort & Cost'!E17*0.7+'5. Other Costs'!$E$18*0.2 -> 128002.5 | E16: ='4. Phase Effort & Cost'!E17*0.3+'4. Phase Effort & Cost'!F17*0.7+'5. Other Costs'!$E$18*0.2 -> 149550 | F16: ='4. Phase Effort & Cost'!F17*0.3+'4. Phase Effort & Cost'!G17+'4. Phase Effort & Cost'!H17*0.5+'5. Other Costs'!$E$18*0.3 -> 192962.5 | G16: ='4. Phase Effort & Cost'!H17*0.5+'4. Phase Effort & Cost'!I17+'5. Other Costs'!$E$18*0.2 -> 116640
B17: Net cash flow | C17: =C15-C16 -> 248085.21 | D17: =D15-D16 -> -128002.5 | E17: =E15-E16 -> 137355.21 | F17: =F15-F16 -> 151323.75 | G17: =G15-G16 -> 112884.17
B18: Cumulative net cash flow | C18: =C17 -> 248085.21 | D18: =C18+D17 -> 120082.71 | E18: =D18+E17 -> 257437.92 | F18: =E18+F17 -> 408761.67 | G18: =F18+G17 -> 521645.83
B20: Note: cash-out assumes uniform burn within month; refine if monthly invoicing differs from phase boundaries.

Sheet 10. Sensitivity
B2: What-If Scenarios — How Much Do We Earn?
B3: IN PLAIN ENGLISH: What if fewer SMBs sign up? What if our rev-share is 10% instead of 15%? This grid shows our total 3-year revenue under 9 different scenarios (3 adoption levels × 3 rev-share rates).
B5: A. Adoption scenarios — average paying tenants per year
B6: Scenario | C6: Year 1 (avg) | D6: Year 2 (avg) | E6: Year 3 (avg) | F6: Notes
B7: Low — slow ramp | C7: 250 | D7: 1000 | E7: 2000 | F7: Conservative: 500 EOY1, 1,500 EOY2, 2,500 EOY3.
B8: Mid — baseline (per Sheet 8) | C8: 375 | D8: 1500 | E8: 3125 | F8: Baseline used in Sheet 8.
B9: High — strong adoption | C9: 500 | D9: 2000 | E9: 4500 | F9: 1,000 EOY1, 3,000 EOY2, 5,500 EOY3.
B11: Blended ARPU (USD/month, 3-year avg) | C11: 65 | F11: Editable. Used for sensitivity calcs below.
B13: B. AIdeology 3-year rev-share revenue (USD) — Scenario × Rev-share %
B14: Adoption scenario | C14: 10% rev-share | D14: 15% rev-share | E14: 20% rev-share | F14: Notes
B15: Low — slow ramp | C15: =(C7+D7+E7)*$C$11*12*0.1 -> 253500 | D15: =(C7+D7+E7)*$C$11*12*0.15 -> 380250 | E15: =(C7+D7+E7)*$C$11*12*0.2 -> 507000 | F15: 3-year cumulative AIdeology rev-share at fixed % rate.
B16: Mid — baseline (per Sheet 8) | C16: =(C8+D8+E8)*$C$11*12*0.1 -> 390000 | D16: =(C8+D8+E8)*$C$11*12*0.15 -> 585000 | E16: =(C8+D8+E8)*$C$11*12*0.2 -> 780000 | F16: 3-year cumulative AIdeology rev-share at fixed % rate.
B17: High — strong adoption | C17: =(C9+D9+E9)*$C$11*12*0.1 -> 546000 | D17: =(C9+D9+E9)*$C$11*12*0.15 -> 819000 | E17: =(C9+D9+E9)*$C$11*12*0.2 -> 1092000 | F17: 3-year cumulative AIdeology rev-share at fixed % rate.
B19: C. Total AIdeology 3-year revenue (fees + rev-share)
B20: Adoption scenario | C20: 10% rev-share | D20: 15% rev-share | E20: 20% rev-share | F20: Notes
B21: Low — slow ramp | C21: ='7. Pricing Summary'!$C$29+C15 -> 3697120.8 | D21: ='7. Pricing Summary'!$C$29+D15 -> 3823870.8 | E21: ='7. Pricing Summary'!$C$29+E15 -> 3950620.8 | F21: Total = fixed-fee envelope (Sheet 7) + 3-year rev-share at chosen %.
B22: Mid — baseline (per Sheet 8) | C22: ='7. Pricing Summary'!$C$29+C16 -> 3833620.8 | D22: ='7. Pricing Summary'!$C$29+D16 -> 4028620.8 | E22: ='7. Pricing Summary'!$C$29+E16 -> 4223620.8 | F22: Total = fixed-fee envelope (Sheet 7) + 3-year rev-share at chosen %.
B23: High — strong adoption | C23: ='7. Pricing Summary'!$C$29+C17 -> 3989620.8 | D23: ='7. Pricing Summary'!$C$29+D17 -> 4262620.8 | E23: ='7. Pricing Summary'!$C$29+E17 -> 4535620.8 | F23: Total = fixed-fee envelope (Sheet 7) + 3-year rev-share at chosen %.
