Workbook

Sheet 1. Cover & Assumptions
B2: AIdeology — Internal Pricing & Staffing Analysis
B3: ADNOC Loyalty AI Programme · Subcontract to HPE · v0.1 DRAFT
B4: INTERNAL — NOT FOR HPE OR ADNOC. Pricing model for AIdeology team only.
B5: Date: 2026-04-30
B7: How to use this workbook
B8: • All blue-text cells are editable inputs (rates, allocations, durations, margins).
B9: • All yellow-highlighted cells are key assumptions to confirm before sending pricing to HPE.
B10: • All black-text cells are calculated formulas — do not overwrite.
B11: • Green-text cells are links to other sheets in this workbook.
B12: • Sheet 2: Roles & Rates — adjust daily costs and bill rates here.
B13: • Sheet 3: Phase Staffing — adjust headcount and allocation % per phase.
B14: • Sheet 4: Phase Effort & Cost — calculated from staffing × rates.
... B22: Global assumptions
B23: Assumption | C23: Value | D23: Unit | E23: Notes / source
B24: Programme duration | C24: 16 | D24: weeks | E24: Per SOW §5.1 — 3–4 month delivery, single-phase on-prem.
B25: Working days per week | C25: 5 | D25: days | E25: Standard.
B26: Hours per working day | C26: 8 | D26: hours | E26: Standard.
B27: Currency | C27: USD | D27: — | E27: Internal model; final pricing to HPE may be issued in AED or USD.
B28: FX assumption (USD→AED) | C28: 3.67 | D28: rate | E28: Pegged.
B29: AIdeology target gross margin | C29: 0.35 | D29: % | E29: Target margin on cost before HPE markup. Adjust for win-rate.
B30: Contingency on direct cost | C30: 0.1 | D30: % | E30: Buffer for unknowns (sandbox slip, pen-test rework, etc.).
B31: Risk reserve (held back) | C31: 0.05 | D31: % | E31: Held internally; not in price to HPE.
B32: HPE markup (illustrative) | C32: 0.2 | D32: % | E32: ILLUSTRATIVE only — HPE sets its own markup. Not in our pricing.
B33: Concurrency baseline | C33: 25k | D33: scenario | E33: Mid scenario per SOW §3.5. Sensitivity sheet covers 10k / 25k / 50k.
B36: Important disclaimers
B37: • Daily rates in Sheet 2 are PLACEHOLDER values for AIdeology to validate against actual cost structure.
B38: • Headcount and allocation % per phase are AIdeology's first-pass sizing. Adjust based on actual team capacity.
B39: • Voice provider on-prem cost (11Labs) on Sheet 5 is an estimate pending vendor quote.
B40: • GPU loan from HPE is assumed at no charge for the bridge period; if HPE charges, add to Sheet 5.
B41: • All non-personnel costs are estimates only; obtain firm quotes before issuing commercial annex to HPE.

Sheet 2. Roles & Rates
B2: Roles & Daily Rates
B3: Daily rates in USD. Internal cost = AIdeology fully-loaded cost. Bill rate = what we charge HPE before margin applied at programme level (Sheet 6).
B5: Role | C5: Seniority | D5: Internal cost / day (USD) | E5: Bill rate / day (USD) | F5: Notes
B6: Engagement / Programme Manager | C6: Senior | D6: 1100 | E6: 1850 | F6: Single point of contact to HPE PMO; weekly governance.
B7: Solution Architect (Lead) | C7: Principal | D7: 1100 | E7: 2150 | F7: Owns HLD/LLD; latency budget; sizing scenarios.
B8: AI / LLM Engineer — Orchestration & Reasoning | C8: Senior | D8: 900 | E8: 1750 | F8: Markdown rules engine, FSM, tool-calling. LLM service, prompt management, guardrails.
B9: Voice / Conversational Engineer | C9: Senior | D9: 900 | E9: 1750 | F9: 11Labs on-prem, fillers, barge-in.
B10: Data & Integration Engineer | C10: Senior | D10: 950 | E10: 1550 | F10: Oracle DW views, local cache, PII masking pipeline. MCP server + 6 ADNOC adapters.
B11: Frontend / UX Engineer | C11: Mid | D11: 800 | E11: 1300 | F11: Operator / Manager / Admin consoles.
B12: DevOps / Platform Engineer | C12: Senior | D12: 950 | E12: 1550 | F12: Helm, Terraform, CI/CD, Grafana/Loki.
B13: QA Engineer | C13: Mid | D13: 750 | E13: 1200 | F13: UAT pack, synthetic data, automated tests.
B14: Security / Compliance Lead | C14: Senior | D14: 1100 | E14: 1750 | F14: PII residency, GDPR alignment, pen-test support.
B16: Total roles in plan: 9

Sheet 3. Phase Staffing
B2: Phase Staffing — Person-weeks per Role per Phase
B3: Each cell = (headcount × % allocation × phase duration in weeks). Edit headcount and allocation in the editable section below.
B5: Role | C5: P1 — Mobilisation & Discovery | D5: P2 — Architecture & Prototype | E5: P3 — Build (core + integrations) | F5: P4 — Integration & Hardening | G5: P5 — Pilot & Phase-1 Expansion | H5: P6 — Hand-over & Hypercare | I5: Total p-weeks
B6: Phase duration (weeks) | C6: 2 | D6: 2 | E6: 4 | F6: 2 | G6: 4 | H6: 2 | I6: —
B7: Engagement / Programme Manager | C7: =C23*C36*C6 -> 1 | D7: =D23*D36*D6 -> 1 | E7: =E23*E36*E6 -> 2.4 | F7: =F23*F36*F6 -> 1.4 | G7: =G23*G36*G6 -> 2.8 | H7: =H23*H36*H6 -> 1 | I7: =SUM(C7:H7) -> 9.6
B8: Solution Architect (Lead) | C8: =C24*C37*C6 -> 2 | D8: =D24*D37*D6 -> 2 | E8: =E24*E37*E6 -> 3.2 | F8: =F24*F37*F6 -> 1.2 | G8: =G24*G37*G6 -> 1.6 | H8: =H24*H37*H6 -> 0.6 | I8: =SUM(C8:H8) -> 10.6
B9: AI / LLM Engineer — Reasoning | C9: =C25*C38*C6 -> 1 | D9: =D25*D38*D6 -> 2 | E9: =E25*E38*E6 -> 8 | F9: =F25*F38*F6 -> 4 | G9: =G25*G38*G6 -> 2.4 | H9: =H25*H38*H6 -> 0.8 | I9: =SUM(C9:H9) -> 18.2
B10: Voice / Conversational Engineer | C10: =C26*C39*C6 -> 1 | D10: =D26*D39*D6 -> 1.6 | E10: =E26*E39*E6 -> 8 | F10: =F26*F39*F6 -> 2 | G10: =G26*G39*G6 -> 2.4 | H10: =H26*H39*H6 -> 0 | I10: =SUM(C10:H10) -> 15
B11: Data Engineer | C11: =C27*C40*C6 -> 1 | D11: =D27*D40*D6 -> 1.6 | E11: =E27*E40*E6 -> 3.2 | F11: =F27*F40*F6 -> 1.6 | G11: =G27*G40*G6 -> 2 | H11: =H27*H40*H6 -> 0 | I11: =SUM(C11:H11) -> 9.4
B12: Frontend / UX Engineer | C12: =C28*C41*C6 -> 1 | D12: =D28*D41*D6 -> 1.2 | E12: =E28*E41*E6 -> 4 | F12: =F28*F41*F6 -> 1.6 | G12: =G28*G41*G6 -> 2 | H12: =H28*H41*H6 -> 0 | I12: =SUM(C12:H12) -> 9.8
B13: DevOps / Platform Engineer | C13: =C29*C42*C6 -> 1.6 | D13: =D29*D42*D6 -> 3.2 | E13: =E29*E42*E6 -> 3.2 | F13: =F29*F42*F6 -> 1.6 | G13: =G29*G42*G6 -> 3.2 | H13: =H29*H42*H6 -> 1 | I13: =SUM(C13:H13) -> 13.8
B14: QA Engineer | C14: =C30*C43*C6 -> 0 | D14: =D30*D43*D6 -> 0 | E14: =E30*E43*E6 -> 2 | F14: =F30*F43*F6 -> 2 | G14: =G30*G43*G6 -> 8 | H14: =H30*H43*H6 -> 1 | I14: =SUM(C14:H14) -> 13
B15: Security / Compliance Lead | C15: =C31*C44*C6 -> 1 | D15: =D31*D44*D6 -> 1 | E15: =E31*E44*E6 -> 1.2 | F15: =F31*F44*F6 -> 1 | G15: =G31*G44*G6 -> 1.2 | H15: =H31*H44*H6 -> 0 | I15: =SUM(C15:H15) -> 5.4
B16: Total person-weeks per phase | C16: =SUM(C7:C15) -> 9.6 | D16: =SUM(D7:D15) -> 13.6 | E16: =SUM(E7:E15) -> 35.2 | F16: =SUM(F7:F15) -> 16.4 | G16: =SUM(G7:G15) -> 25.6 | H16: =SUM(H7:H15) -> 4.4 | I16: =SUM(C16:H16) -> 104.8
B18: EDITABLE — Headcount and Allocation % per Role per Phase
B19: Format per cell: HEADCOUNT × ALLOCATION%. Edit in the two sub-rows below per role.
B21: Headcount per phase (number of people).
B22: Role | C22: P1 — Mobilisation & Discovery | D22: P2 — Architecture & Prototype | E22: P3 — Build (core + integrations) | F22: P4 — Integration & Hardening | G22: P5 — Pilot & Phase-1 Expansion | H22: P6 — Hand-over & Hypercare
B23: Engagement / Programme Manager | C23: 1 | D23: 1 | E23: 1 | F23: 1 | G23: 1 | H23: 1
B24: Solution Architect (Lead) | C24: 1 | D24: 1 | E24: 1 | F24: 1 | G24: 1 | H24: 1
B25: AI / LLM Engineer — Reasoning | C25: 1 | D25: 1 | E25: 2 | F25: 2 | G25: 1 | H25: 1
B26: Voice / Conversational Engineer | C26: 1 | D26: 1 | E26: 2 | F26: 1 | G26: 1 | H26: 0
B27: Data Engineer | C27: 1 | D27: 1 | E27: 1 | F27: 1 | G27: 1 | H27: 0
B28: Frontend / UX Engineer | C28: 1 | D28: 1 | E28: 1 | F28: 1 | G28: 1 | H28: 0
B29: DevOps / Platform Engineer | C29: 1 | D29: 2 | E29: 1 | F29: 1 | G29: 1 | H29: 1
B30: QA Engineer | C30: 0 | D30: 0 | E30: 1 | F30: 1 | G30: 2 | H30: 1
B31: Security / Compliance Lead | C31: 1 | D31: 1 | E31: 1 | F31: 1 | G31: 1 | H31: 0
B34: Allocation % per phase (share of time on this programme).
B35: Role | C35: P1 — Mobilisation & Discovery | D35: P2 — Architecture & Prototype | E35: P3 — Build (core + integrations) | F35: P4 — Integration & Hardening | G35: P5 — Pilot & Phase-1 Expansion | H35: P6 — Hand-over & Hypercare
B36: Engagement / Programme Manager | C36: 0.5 | D36: 0.5 | E36: 0.6 | F36: 0.7 | G36: 0.7 | H36: 0.5
B37: Solution Architect (Lead) | C37: 1 | D37: 1 | E37: 0.8 | F37: 0.6 | G37: 0.4 | H37: 0.3
B38: AI / LLM Engineer — Reasoning | C38: 0.5 | D38: 1 | E38: 1 | F38: 1 | G38: 0.6 | H38: 0.4
B39: Voice / Conversational Engineer | C39: 0.5 | D39: 0.8 | E39: 1 | F39: 1 | G39: 0.6 | H39: 0
B40: Data Engineer | C40: 0.5 | D40: 0.8 | E40: 0.8 | F40: 0.8 | G40: 0.5 | H40: 0
B41: Frontend / UX Engineer | C41: 0.5 | D41: 0.6 | E41: 1 | F41: 0.8 | G41: 0.5 | H41: 0
B42: DevOps / Platform Engineer | C42: 0.8 | D42: 0.8 | E42: 0.8 | F42: 0.8 | G42: 0.8 | H42: 0.5
B43: QA Engineer | C43: 0 | D43: 0 | E43: 0.5 | F43: 1 | G43: 1 | H43: 0.5
B44: Security / Compliance Lead | C44: 0.5 | D44: 0.5 | E44: 0.3 | F44: 0.5 | G44: 0.3 | H44: 0

Sheet 4. Phase Effort & Cost
B2: Phase Effort & Cost — Internal Cost basis
B3: Cost per role per phase = person-weeks (Sheet 3) × days per week × internal cost/day (Sheet 2). Bill view repeats with bill rates.
B5: A. INTERNAL COST (fully-loaded AIdeology cost)
B6: Role | C6: Cost / day | D6: P1 — Mobilisation & Discovery | E6: P2 — Architecture & Prototype | F6: P3 — Build (core + integrations) | G6: P4 — Integration & Hardening | H6: P5 — Pilot & Phase-1 Expansion | I6: P6 — Hand-over & Hypercare | J6: Total cost | K6: % of total
B7: Engagement / Programme Manager | C7: 500 | D7: ='3. Phase Staffing'!C7*'1. Cover & Assumptions'!$C$25*$C7 -> 2500 | E7: ='3. Phase Staffing'!D7*'1. Cover & Assumptions'!$C$25*$C7 -> 2500 | F7: ='3. Phase Staffing'!E7*'1. Cover & Assumptions'!$C$25*$C7 -> 6000 | G7: ='3. Phase Staffing'!F7*'1. Cover & Assumptions'!$C$25*$C7 -> 3500 | H7: ='3. Phase Staffing'!G7*'1. Cover & Assumptions'!$C$25*$C7 -> 7000 | I7: ='3. Phase Staffing'!H7*'1. Cover & Assumptions'!$C$25*$C7 -> 2500 | J7: =SUM(D7:I7) -> 24000 | K7: =IFERROR(J7/$J$16,0) -> 0.086736538
B8: Solution Architect (Lead) | C8: 600 | D8: ='3. Phase Staffing'!C8*'1. Cover & Assumptions'!$C$25*$C8 -> 6000 | E8: ='3. Phase Staffing'!D8*'1. Cover & Assumptions'!$C$25*$C8 -> 6000 | F8: ='3. Phase Staffing'!E8*'1. Cover & Assumptions'!$C$25*$C8 -> 9600 | G8: ='3. Phase Staffing'!F8*'1. Cover & Assumptions'!$C$25*$C8 -> 3600 | H8: ='3. Phase Staffing'!G8*'1. Cover & Assumptions'!$C$25*$C8 -> 4800 | I8: ='3. Phase Staffing'!H8*'1. Cover & Assumptions'!$C$25*$C8 -> 1800 | J8: =SUM(D8:I8) -> 31800 | K8: =IFERROR(J8/$J$16,0) -> 0.11492591
B9: AI / LLM Engineer — Reasoning | C9: 600 | D9: ='3. Phase Staffing'!C9*'1. Cover & Assumptions'!$C$25*$C9 -> 3000 | E9: ='3. Phase Staffing'!D9*'1. Cover & Assumptions'!$C$25*$C9 -> 6000 | F9: ='3. Phase Staffing'!E9*'1. Cover & Assumptions'!$C$25*$C9 -> 24000 | G9: ='3. Phase Staffing'!F9*'1. Cover & Assumptions'!$C$25*$C9 -> 12000 | H9: ='3. Phase Staffing'!G9*'1. Cover & Assumptions'!$C$25*$C9 -> 7200 | I9: ='3. Phase Staffing'!H9*'1. Cover & Assumptions'!$C$25*$C9 -> 2400 | J9: =SUM(D9:I9) -> 54600 | K9: =IFERROR(J9/$J$16,0) -> 0.19732562
B10: Voice / Conversational Engineer | C10: 600 | D10: ='3. Phase Staffing'!C10*'1. Cover & Assumptions'!$C$25*$C10 -> 3000 | E10: ='3. Phase Staffing'!D10*'1. Cover & Assumptions'!$C$25*$C10 -> 4800 | F10: ='3. Phase Staffing'!E10*'1. Cover & Assumptions'!$C$25*$C10 -> 24000 | G10: ='3. Phase Staffing'!F10*'1. Cover & Assumptions'!$C$25*$C10 -> 6000 | H10: ='3. Phase Staffing'!G10*'1. Cover & Assumptions'!$C$25*$C10 -> 7200 | I10: ='3. Phase Staffing'!H10*'1. Cover & Assumptions'!$C$25*$C10 -> 0 | J10: =SUM(D10:I10) -> 45000 | K10: =IFERROR(J10/$J$16,0) -> 0.16263101
B11: Data Engineer | C11: 500 | D11: ='3. Phase Staffing'!C11*'1. Cover & Assumptions'!$C$25*$C11 -> 2500 | E11: ='3. Phase Staffing'!D11*'1. Cover & Assumptions'!$C$25*$C11 -> 4000 | F11: ='3. Phase Staffing'!E11*'1. Cover & Assumptions'!$C$25*$C11 -> 8000 | G11: ='3. Phase Staffing'!F11*'1. Cover & Assumptions'!$C$25*$C11 -> 4000 | H11: ='3. Phase Staffing'!G11*'1. Cover & Assumptions'!$C$25*$C11 -> 5000 | I11: ='3. Phase Staffing'!H11*'1. Cover & Assumptions'!$C$25*$C11 -> 0 | J11: =SUM(D11:I11) -> 23500 | K11: =IFERROR(J11/$J$16,0) -> 0.084929527
B12: Frontend / UX Engineer | C12: 400 | D12: ='3. Phase Staffing'!C12*'1. Cover & Assumptions'!$C$25*$C12 -> 2000 | E12: ='3. Phase Staffing'!D12*'1. Cover & Assumptions'!$C$25*$C12 -> 2400 | F12: ='3. Phase Staffing'!E12*'1. Cover & Assumptions'!$C$25*$C12 -> 8000 | G12: ='3. Phase Staffing'!F12*'1. Cover & Assumptions'!$C$25*$C12 -> 3200 | H12: ='3. Phase Staffing'!G12*'1. Cover & Assumptions'!$C$25*$C12 -> 4000 | I12: ='3. Phase Staffing'!H12*'1. Cover & Assumptions'!$C$25*$C12 -> 0 | J12: =SUM(D12:I12) -> 19600 | K12: =IFERROR(J12/$J$16,0) -> 0.070834839
B13: DevOps / Platform Engineer | C13: 600 | D13: ='3. Phase Staffing'!C13*'1. Cover & Assumptions'!$C$25*$C13 -> 4800 | E13: ='3. Phase Staffing'!D13*'1. Cover & Assumptions'!$C$25*$C13 -> 9600 | F13: ='3. Phase Staffing'!E13*'1. Cover & Assumptions'!$C$25*$C13 -> 9600 | G13: ='3. Phase Staffing'!F13*'1. Cover & Assumptions'!$C$25*$C13 -> 4800 | H13: ='3. Phase Staffing'!G13*'1. Cover & Assumptions'!$C$25*$C13 -> 9600 | I13: ='3. Phase Staffing'!H13*'1. Cover & Assumptions'!$C$25*$C13 -> 3000 | J13: =SUM(D13:I13) -> 41400 | K13: =IFERROR(J13/$J$16,0) -> 0.14962053
B14: QA Engineer | C14: 400 | D14: ='3. Phase Staffing'!C14*'1. Cover & Assumptions'!$C$25*$C14 -> 0 | E14: ='3. Phase Staffing'!D14*'1. Cover & Assumptions'!$C$25*$C14 -> 0 | F14: ='3. Phase Staffing'!E14*'1. Cover & Assumptions'!$C$25*$C14 -> 4000 | G14: ='3. Phase Staffing'!F14*'1. Cover & Assumptions'!$C$25*$C14 -> 4000 | H14: ='3. Phase Staffing'!G14*'1. Cover & Assumptions'!$C$25*$C14 -> 16000 | I14: ='3. Phase Staffing'!H14*'1. Cover & Assumptions'!$C$25*$C14 -> 2000 | J14: =SUM(D14:I14) -> 26000 | K14: =IFERROR(J14/$J$16,0) -> 0.093964583
B15: Security / Compliance Lead | C15: 400 | D15: ='3. Phase Staffing'!C15*'1. Cover & Assumptions'!$C$25*$C15 -> 2000 | E15: ='3. Phase Staffing'!D15*'1. Cover & Assumptions'!$C$25*$C15 -> 2000 | F15: ='3. Phase Staffing'!E15*'1. Cover & Assumptions'!$C$25*$C15 -> 2400 | G15: ='3. Phase Staffing'!F15*'1. Cover & Assumptions'!$C$25*$C15 -> 2000 | H15: ='3. Phase Staffing'!G15*'1. Cover & Assumptions'!$C$25*$C15 -> 2400 | I15: ='3. Phase Staffing'!H15*'1. Cover & Assumptions'!$C$25*$C15 -> 0 | J15: =SUM(D15:I15) -> 10800 | K15: =IFERROR(J15/$J$16,0) -> 0.039031442
B16: Total internal cost per phase | D16: =SUM(D7:D15) -> 25800 | E16: =SUM(E7:E15) -> 37300 | F16: =SUM(F7:F15) -> 95600 | G16: =SUM(G7:G15) -> 43100 | H16: =SUM(H7:H15) -> 63200 | I16: =SUM(I7:I15) -> 11700 | J16: =SUM(J7:J15) -> 276700 | K16: =IFERROR(J16/J16,0) -> 1

Sheet 5. Other Costs
B2: Other (non-personnel) Costs
B3: Software, cloud, voice provider, travel, contingency. All values are placeholder estimates pending firm quotes.
B5: Cost item | C5: Unit cost | D5: Quantity / months | E5: Total cost | F5: Phase trigger | G5: Notes
B6: 11Labs on-prem licence (estimate) | C6: 15000 | D6: 4 | E6: =C6*D6 -> 60000 | F6: P2–P6 | G6: Pending vendor quote; viability under evaluation per SOW §7.1 A4.
B7: LLM inference licence / model access | C7: 8000 | D7: 4 | E7: =C7*D7 -> 32000 | F7: P2–P6 | G7: Open-weights deployed on HPE infra; assume nominal licence fee.
B8: Observability stack (Grafana Cloud / Loki) | C8: 1500 | D8: 4 | E8: =C8*D8 -> 6000 | F8: P1–P6 | G8: Hosted observability for the team during build.
B9: CI/CD & repo hosting | C9: 800 | D9: 4 | E9: =C9*D9 -> 3200 | F9: P1–P6 | G9: GitHub Enterprise / equivalent.
B10: Security tooling (SAST/DAST/SCA) | C10: 2500 | D10: 4 | E10: =C10*D10 -> 10000 | F10: P1–P6 | G10: Snyk / Checkmarx etc.
B11: Pen-test (third-party) | C11: 25000 | D11: 1 | E11: =C11*D11 -> 25000 | F11: P4 | G11: External pen-test before pilot go-live.
B12: Travel — UAE (per trip, 3 people, 5 days) | C12: 9000 | D12: 4 | E12: =C12*D12 -> 36000 | F12: P1–P5 | G12: On-site mobilisation, integration, UAT, pilot go-live.
B13: Demo / event support (Make in the UAE) | C13: 5000 | D13: 1 | E13: =C13*D13 -> 5000 | F13: P1 | G13: Per Schedule A action.
B14: Misc (printing, demos, contingencies) | C14: 3000 | D14: 4 | E14: =C14*D14 -> 12000 | F14: All | G14: Petty cash for the engagement.
B15: Total other costs (subtotal) | E15: =SUM(E6:E14) -> 189200

Sheet 6. Pricing Summary
B2: Pricing Summary — From Internal Cost to Price-to-HPE
B3: Walks the cost stack: personnel + non-personnel + contingency + AIdeology margin = Price to HPE. HPE markup shown for illustration only.
B5: Component | C5: Value (USD) | D5: Notes
B6: Personnel cost — internal (sum of phases) | C6: ='4. Phase Effort & Cost'!$J$16 -> 276700 | D6: From Sheet 4 (cost basis).
B7: Other costs — non-personnel | C7: ='5. Other Costs'!$E$15 -> 189200 | D7: From Sheet 5.
B8: Subtotal — direct cost | C8: =C6+C7 -> 465900 | D8: Personnel + non-personnel.
B9: Contingency on direct cost | C9: =C8*'1. Cover & Assumptions'!$C$30 -> 46590 | D9: % from Sheet 1.
B10: Total fully-loaded cost | C10: =C8+C9 -> 512490 | D10: Direct cost + contingency.
B11: AIdeology margin on cost | C11: =C10/(1-'1. Cover & Assumptions'!$C$29)-C10 -> 275956.15 | D11: Margin grossed up: price = cost / (1 - margin).
B12: Price to HPE (excl. risk reserve) | C12: =C10+C11 -> 788446.15 | D12: What we propose to charge HPE.
B13: Effective margin % | C13: =IFERROR((C12-C10)/C12,0) -> 0.35 | D13: Should approximate target margin from Sheet 1.
B15: ILLUSTRATIVE — HPE markup | C15: =C12*'1. Cover & Assumptions'!$C$32 -> 157689.23 | D15: HPE sets its own markup. This is for our internal awareness only.
B16: ILLUSTRATIVE — Price to ADNOC (post-HPE markup) | C16: =C12+C15 -> 946135.38 | D16: What ADNOC may pay if HPE applies the assumed markup.
B18: Risk reserve (held internally — not in price) | C18: =C10*'1. Cover & Assumptions'!$C$31 -> 25624.5 | D18: Held at AIdeology level for genuine risk events.
B19: Memo — net AIdeology gross margin after risk reserve | C19: =C12-C10-C18 -> 250331.65 | D19: Useful internal management number.

Sheet 7. Payment Milestones
B2: Payment Milestones — Price-to-HPE distributed across 4 trigger events
B3: Triggered by SOW deliverables. Total = 100% of Price to HPE. Sum check at the bottom must equal Price to HPE.
B5: # | C5: Milestone / trigger | D5: % of price | E5: Target week | F5: Amount (USD) | G5: Acceptance criteria
B6: 1 | C6: Mobilisation & SOW signature (kickoff) | D6: 0.25 | E6: T + 0 | F6: =D6*'6. Pricing Summary'!$C$12 -> 197111.54 | G6: SOW signed; team mobilised within 48h; SOW Schedule A traceability accepted.
B7: 2 | C7: Architecture acceptance + integration sandbox live | D7: 0.3 | E7: T + 4 wk | F7: =D7*'6. Pricing Summary'!$C$12 -> 236533.85 | G7: M3 (HLD accepted) + M5 (MCP server v1 + first 3 ADNOC integrations wired).
B8: 3 | C8: Pilot go-live (limited cohort) | D8: 0.3 | E8: T + 12 wk | F8: =D8*'6. Pricing Summary'!$C$12 -> 236533.85 | G8: M9 (pilot go-live) — Subcontractor confirms deployment; HPE/ADNOC validate first 5 days.
B9: 4 | C9: Final acceptance & hand-over | D9: 0.15 | E9: T + 16 wk | F9: =D9*'6. Pricing Summary'!$C$12 -> 118266.92 | G9: M11 (hand-over to HPE service ops + SLA validation period commenced).
C10: Sum check | D10: =SUM(D6:D9) -> 1 | F10: =SUM(F6:F9) -> 788446.15
B14: Indicative monthly cash-flow (months from kickoff)
B15: Item | C15: M0 (kickoff) | D15: M1 | E15: M2 | F15: M3 (pilot go-live) | G15: M4 (hand-over)
B16: Cash IN (payments from HPE) | C16: =F6 -> 197111.54 | D16: =F7 -> 236533.85 | E16: 0 | F16: =F8 -> 236533.85 | G16: =F9 -> 118266.92
B17: Cash OUT (AIdeology cost burn, est.) | C17: 0 | D17: ='4. Phase Effort & Cost'!D16+'4. Phase Effort & Cost'!E16+'5. Other Costs'!$E$15*0.2 -> 100940 | E17: ='4. Phase Effort & Cost'!F16+'5. Other Costs'!$E$15*0.3 -> 152360 | F17: ='4. Phase Effort & Cost'!G16+'4. Phase Effort & Cost'!H16*0.5+'5. Other Costs'!$E$15*0.3 -> 131460 | G17: ='4. Phase Effort & Cost'!H16*0.5+'4. Phase Effort & Cost'!I16+'5. Other Costs'!$E$15*0.2 -> 81140
B18: Net cash flow | C18: =C16-C17 -> 197111.54 | D18: =D16-D17 -> 135593.85 | E18: =E16-E17 -> -152360 | F18: =F16-F17 -> 105073.85 | G18: =G16-G17 -> 37126.923
B19: Cumulative net cash flow | C19: =C18 -> 197111.54 | D19: =C19+D18 -> 332705.38 | E19: =D19+E18 -> 180345.38 | F19: =E19+F18 -> 285419.23 | G19: =F19+G18 -> 322546.15
B21: Note: cash-out assumes uniform burn within month; refine if monthly invoicing differs from phase boundaries.

Sheet 8. Sensitivity
B2: Sensitivity — Cost & Price by Concurrency Scenario
B3: Three concurrency design points per SOW §3.5. Effort uplift modelled as a multiplier on personnel cost.
B5: Scenario | C5: Effort uplift | D5: Personnel cost | E5: Other costs uplift | F5: Total fully-loaded cost | G5: Notes
B6: 10k concurrent users | C6: 0.85 | D6: ='4. Phase Effort & Cost'!$J$16*C6 -> 235195 | E6: 0.9 | F6: =(D6+'5. Other Costs'!$E$15*E6)*(1+'1. Cover & Assumptions'!$C$30) -> 446022.5 | G6: Lighter sizing; smaller cluster, fewer integrations stress points.
B7: 25k concurrent users (baseline) | C7: 1 | D7: ='4. Phase Effort & Cost'!$J$16*C7 -> 276700 | E7: 1 | F7: =(D7+'5. Other Costs'!$E$15*E7)*(1+'1. Cover & Assumptions'!$C$30) -> 512490 | G7: Baseline assumed in main sheets.
B8: 50k concurrent users | C8: 1.3 | D8: ='4. Phase Effort & Cost'!$J$16*C8 -> 359710 | E8: 1.2 | F8: =(D8+'5. Other Costs'!$E$15*E8)*(1+'1. Cover & Assumptions'!$C$30) -> 645425 | G8: Heavier sizing; more parallelism, additional NFR work.
B11: Scenario | C11: Total fully-loaded cost | D11: Margin | E11: Price to HPE | F11: Δ vs baseline | G11: Notes
B12: 10k concurrent users | C12: =F6 -> 446022.5 | D12: =C12/(1-'1. Cover & Assumptions'!$C$29)-C12 -> 240165.96 | E12: =C12+D12 -> 686188.46 | F12: =IFERROR(E12/'6. Pricing Summary'!$C$12-1,0) -> -0.12969521 | G12: Lighter sizing; smaller cluster, fewer integrations stress points.
B13: 25k concurrent users (baseline) | C13: =F7 -> 512490 | D13: =C13/(1-'1. Cover & Assumptions'!$C$29)-C13 -> 275956.15 | E13: =C13+D13 -> 788446.15 | F13: =IFERROR(E13/'6. Pricing Summary'!$C$12-1,0) -> 0 | G13: Baseline assumed in main sheets.
B14: 50k concurrent users | C14: =F8 -> 645425 | D14: =C14/(1-'1. Cover & Assumptions'!$C$29)-C14 -> 347536.54 | E14: =C14+D14 -> 992961.54 | F14: =IFERROR(E14/'6. Pricing Summary'!$C$12-1,0) -> 0.25939043 | G14: Heavier sizing; more parallelism, additional NFR work.
